{
  "typography": {
    "$type": "dimension",
    "progress-bar": {
      "font-size": {
        "source": "$progress-font-size",
        "$value": "calc({typography.font.size.base} * .75)"
      }
    }
  },
  "size": {
    "$type": "dimension",
    "progress-bar": {
      "height": {
        "base": {
          "source": "$progress-height",
          "$value": "1rem"
        },
        "annotated": {
          "source": "$annotated-progress-height",
          "$value": ".3125rem"
        }
      },
      "border": {
        "width": {
          "source": "$progress-bar-border-width",
          "$value": "1px"
        },
        "radius": {
          "source": "$progress-border-radius",
          "$value": "0"
        }
      },
      "threshold-circle": {
        "source": "$progress-threshold-circle",
        "$value": ".5625rem"
      }
    }
  },
  "spacing": {
    "$type": "dimension",
    "progress-bar": {
      "hint": {
        "annotation-gap": {
          "source": "$progress-hint-annotation-gap",
          "$value": ".5rem"
        }
      }
    }
  },
  "transition": {
    "$type": "transition",
    "progress-bar": {
      "bar": {
        "animation-timing": {
          "source": "$progress-bar-animation-timing",
          "$value": "1s linear infinite"
        },
        "transition": {
          "source": "$progress-bar-transition",
          "$value": "width .6s ease"
        }
      }
    }
  }
}
