{"$component-active-bg":"var(--pgn-color-background-active)","$text-black-50":"var(--pgn-color-text-50-black)","$text-white-50":"var(--pgn-color-text-50-white)","$component-active-color":"var(--pgn-color-active)","$border-color":"var(--pgn-color-border)","$border-width":"var(--pgn-size-border-width)","$border-radius":"var(--pgn-size-border-radius-base)","$border-radius-lg":"var(--pgn-size-border-radius-lg)","$border-radius-sm":"var(--pgn-size-border-radius-sm)","$action-row-gap-x":"var(--pgn-spacing-action-row-gap-x)","$action-row-gap-y":"var(--pgn-spacing-action-row-gap-y)","$alert-padding-y":"var(--pgn-spacing-alert-padding-y)","$alert-padding-x":"var(--pgn-spacing-alert-padding-x)","$alert-margin-bottom":"var(--pgn-spacing-alert-margin-bottom)","$alert-actions-gap":"var(--pgn-spacing-alert-actions-gap)","$alert-icon-space":"var(--pgn-spacing-alert-icon-space)","$alert-link-font-weight":"var(--pgn-typography-alert-font-weight-link)","$alert-font-size":"var(--pgn-typography-alert-font-size)","$alert-line-height":"var(--pgn-typography-alert-line-height)","$alert-title-color":"var(--pgn-color-alert-title)","$alert-content-color":"var(--pgn-color-alert-content)","$alert-success-icon-color":"var(--pgn-color-alert-icon-success)","$alert-info-icon-color":"var(--pgn-color-alert-icon-info)","$alert-danger-icon-color":"var(--pgn-color-alert-icon-danger)","$alert-warning-icon-color":"var(--pgn-color-alert-icon-warning)","$alert-success-bg":"var(--pgn-color-alert-bg-success)","$alert-info-bg":"var(--pgn-color-alert-bg-info)","$alert-danger-bg":"var(--pgn-color-alert-bg-danger)","$alert-warning-bg":"var(--pgn-color-alert-bg-warning)","$alert-success-border-color":"var(--pgn-color-alert-border-success)","$alert-info-border-color":"var(--pgn-color-alert-border-info)","$alert-danger-border-color":"var(--pgn-color-alert-border-danger)","$alert-warning-border-color":"var(--pgn-color-alert-border-warning)","$alert-box-shadow":"var(--pgn-elevation-alert-box-shadow)","$alert-border-radius":"var(--pgn-size-alert-border-radius)","$alert-border-width":"var(--pgn-size-alert-border-width)","$annotation-padding":"var(--pgn-spacing-annotation-padding)","$annotation-arrow-side-margin":"var(--pgn-spacing-annotation-arrow-side-margin)","$annotation-box-shadow":"var(--pgn-elevation-annotation-box-shadow)","$annotation-font-size":"var(--pgn-typography-annotation-font-size)","$annotation-line-height":"var(--pgn-typography-annotation-line-height)","$annotation-success-color":"var(--pgn-color-annotation-text-success)","$annotation-warning-color":"var(--pgn-color-annotation-text-warning)","$annotation-error-color":"var(--pgn-color-annotation-text-error)","$annotation-light-color":"var(--pgn-color-annotation-text-light)","$annotation-dark-color":"var(--pgn-color-annotation-text-dark)","$annotation-success-bg":"var(--pgn-color-annotation-bg-success)","$annotation-warning-bg":"var(--pgn-color-annotation-bg-warning)","$annotation-error-bg":"var(--pgn-color-annotation-bg-error)","$annotation-light-bg":"var(--pgn-color-annotation-bg-light)","$annotation-dark-bg":"var(--pgn-color-annotation-bg-dark)","$annotation-arrow-border-width":"var(--pgn-size-annotation-arrow-border-width)","$annotation-max-width":"var(--pgn-size-annotation-max-width)","$annotation-border-radius":"var(--pgn-size-annotation-border-radius)","$avatar-color-border":"var(--pgn-color-avatar-border)","$avatar-size":"var(--pgn-size-avatar-base)","$avatar-size-xs":"var(--pgn-size-avatar-xs)","$avatar-size-sm":"var(--pgn-size-avatar-sm)","$avatar-size-lg":"var(--pgn-size-avatar-lg)","$avatar-size-xl":"var(--pgn-size-avatar-xl)","$avatar-size-xxl":"var(--pgn-size-avatar-xxl)","$avatar-size-huge":"var(--pgn-size-avatar-huge)","$avatar-border":"var(--pgn-size-avatar-border-base)","$avatar-border-radius":"var(--pgn-size-avatar-border-radius)","$avatar-button-padding-left":"var(--pgn-spacing-avatar-button-padding-left-base)","$avatar-button-padding-left-sm":"var(--pgn-spacing-avatar-button-padding-left-sm)","$avatar-button-padding-left-lg":"var(--pgn-spacing-avatar-button-padding-left-lg)","$badge-padding-x":"var(--pgn-spacing-badge-padding-x-base)","$badge-pill-padding-x":"var(--pgn-spacing-badge-padding-x-pill)","$badge-padding-y":"var(--pgn-spacing-badge-padding-y)","$badge-font-size":"var(--pgn-typography-badge-font-size)","$badge-font-weight":"var(--pgn-typography-badge-font-weight)","$badge-primary-color":"var(--pgn-color-badge-text-primary)","$badge-secondary-color":"var(--pgn-color-badge-text-secondary)","$badge-success-color":"var(--pgn-color-badge-text-success)","$badge-danger-color":"var(--pgn-color-badge-text-danger)","$badge-warning-color":"var(--pgn-color-badge-text-warning)","$badge-info-color":"var(--pgn-color-badge-text-info)","$badge-light-color":"var(--pgn-color-badge-text-light)","$badge-dark-color":"var(--pgn-color-badge-text-dark)","$badge-primary-bg":"var(--pgn-color-badge-bg-primary)","$badge-secondary-bg":"var(--pgn-color-badge-bg-secondary)","$badge-success-bg":"var(--pgn-color-badge-bg-success)","$badge-warning-bg":"var(--pgn-color-badge-bg-warning)","$badge-danger-bg":"var(--pgn-color-badge-bg-danger)","$badge-info-bg":"var(--pgn-color-badge-bg-info)","$badge-light-bg":"var(--pgn-color-badge-bg-light)","$badge-dark-bg":"var(--pgn-color-badge-bg-dark)","$badge-primary-focus-color":"var(--pgn-color-badge-focus-primary)","$badge-secondary-focus-color":"var(--pgn-color-badge-focus-secondary)","$badge-success-focus-color":"var(--pgn-color-badge-focus-success)","$badge-warning-focus-color":"var(--pgn-color-badge-focus-warning)","$badge-danger-focus-color":"var(--pgn-color-badge-focus-danger)","$badge-info-focus-color":"var(--pgn-color-badge-focus-info)","$badge-light-focus-color":"var(--pgn-color-badge-focus-light)","$badge-dark-focus-color":"var(--pgn-color-badge-focus-dark)","$badge-primary-focus-bg":"var(--pgn-color-badge-focus-bg-primary)","$badge-secondary-focus-bg":"var(--pgn-color-badge-focus-bg-secondary)","$badge-success-focus-bg":"var(--pgn-color-badge-focus-bg-success)","$badge-danger-focus-bg":"var(--pgn-color-badge-focus-bg-danger)","$badge-warning-focus-bg":"var(--pgn-color-badge-focus-bg-warning)","$badge-info-focus-bg":"var(--pgn-color-badge-focus-bg-info)","$badge-light-focus-bg":"var(--pgn-color-badge-focus-bg-light)","$badge-dark-focus-bg":"var(--pgn-color-badge-focus-bg-dark)","$badge-primary-focus-box-shadow-color":"var(--pgn-color-badge-focus-box-shadow-primary)","$badge-secondary-focus-box-shadow-color":"var(--pgn-color-badge-focus-box-shadow-secondary)","$badge-success-focus-box-shadow-color":"var(--pgn-color-badge-focus-box-shadow-success)","$badge-danger-focus-box-shadow-color":"var(--pgn-color-badge-focus-box-shadow-danger)","$badge-warning-focus-box-shadow-color":"var(--pgn-color-badge-focus-box-shadow-warning)","$badge-info-focus-box-shadow-color":"var(--pgn-color-badge-focus-box-shadow-info)","$badge-light-focus-box-shadow-color":"var(--pgn-color-badge-focus-box-shadow-light)","$badge-dark-focus-box-shadow-color":"var(--pgn-color-badge-focus-box-shadow-dark)","$badge-border-radius":"var(--pgn-size-badge-border-radius-base)","$badge-pill-border-radius":"var(--pgn-size-badge-border-radius-pill)","$badge-focus-width":"var(--pgn-size-badge-focus-width)","$badge-transition":"var(--pgn-transition-badge)","$breadcrumb-bg":"var(--pgn-color-breadcrumb-bg)","$breadcrumb-color":"var(--pgn-color-breadcrumb-base)","$breadcrumb-divider-color":"var(--pgn-color-breadcrumb-divider)","$breadcrumb-active-color":"var(--pgn-color-breadcrumb-active)","$breadcrumb-inverse-color":"var(--pgn-color-breadcrumb-inverse-base)","$breadcrumb-inverse-active":"var(--pgn-color-breadcrumb-inverse-active)","$breadcrumb-inverse-spacer":"var(--pgn-color-breadcrumb-inverse-spacer)","$breadcrumb-font-size":"var(--pgn-typography-breadcrumb-font-size)","$breadcrumb-padding-y":"var(--pgn-spacing-breadcrumb-padding-y)","$breadcrumb-padding-x":"var(--pgn-spacing-breadcrumb-padding-x)","$breadcrumb-item-padding":"var(--pgn-spacing-breadcrumb-padding-item)","$breadcrumb-margin-bottom":"var(--pgn-spacing-breadcrumb-margin-bottom)","$breadcrumb-margin-left":"var(--pgn-spacing-breadcrumb-margin-left)","$breadcrumb-border-radius":"var(--pgn-size-breadcrumb-border-radius-base)","$breadcrumb-focus-border-radius":"var(--pgn-size-breadcrumb-border-radius-focus)","$breadcrumb-border-focus-width":"var(--pgn-size-breadcrumb-border-width-focus)","$bubble-success-color":"var(--pgn-color-bubble-text-success)","$bubble-warning-color":"var(--pgn-color-bubble-text-warning)","$bubble-error-color":"var(--pgn-color-bubble-text-error)","$bubble-primary-color":"var(--pgn-color-bubble-text-primary)","$bubble-success-bg":"var(--pgn-color-bubble-bg-success)","$bubble-warning-bg":"var(--pgn-color-bubble-bg-warning)","$bubble-error-bg":"var(--pgn-color-bubble-bg-error)","$bubble-primary-bg":"var(--pgn-color-bubble-bg-primary)","$bubble-expandable-padding-y":"var(--pgn-spacing-bubble-expandable-padding-y)","$bubble-expandable-padding-x":"var(--pgn-spacing-bubble-expandable-padding-x)","$btn-brand-color":"var(--pgn-color-btn-text-brand)","$btn-brand-outline-color":"var(--pgn-color-btn-text-outline-brand)","$btn-brand-inverse-color":"var(--pgn-color-btn-text-inverse-brand)","$btn-brand-inverse-outline-color":"var(--pgn-color-btn-text-inverse-outline-brand)","$btn-brand-bg":"var(--pgn-color-btn-bg-brand)","$btn-brand-inverse-bg":"var(--pgn-color-btn-bg-inverse-brand)","$btn-brand-border-color":"var(--pgn-color-btn-border-brand)","$btn-brand-outline-border-color":"var(--pgn-color-btn-border-outline-brand)","$btn-brand-inverse-outline-border-color":"var(--pgn-color-btn-border-inverse-outline-brand)","$btn-brand-hover-color":"var(--pgn-color-btn-hover-text-brand)","$btn-brand-outline-hover-color":"var(--pgn-color-btn-hover-text-outline-brand)","$btn-brand-inverse-hover-color":"var(--pgn-color-btn-hover-text-inverse-brand)","$btn-brand-inverse-outline-hover-color":"var(--pgn-color-btn-hover-text-inverse-outline-brand)","$btn-brand-hover-bg":"var(--pgn-color-btn-hover-bg-brand)","$btn-brand-outline-hover-bg":"var(--pgn-color-btn-hover-bg-outline-brand)","$btn-brand-inverse-hover-bg":"var(--pgn-color-btn-hover-bg-inverse-brand)","$btn-brand-inverse-outline-hover-bg":"var(--pgn-color-btn-hover-bg-inverse-outline-brand)","$btn-brand-hover-border-color":"var(--pgn-color-btn-hover-border-brand)","$btn-brand-outline-hover-border-color":"var(--pgn-color-btn-hover-border-outline-brand)","$btn-brand-inverse-outline-hover-border-color":"var(--pgn-color-btn-hover-border-inverse-outline-brand)","$btn-brand-active-color":"var(--pgn-color-btn-active-text-brand)","$btn-brand-outline-active-color":"var(--pgn-color-btn-active-text-outline-brand)","$btn-brand-inverse-active-color":"var(--pgn-color-btn-active-text-inverse-brand)","$btn-brand-inverse-outline-active-color":"var(--pgn-color-btn-active-text-inverse-outline-brand)","$btn-brand-active-bg":"var(--pgn-color-btn-active-bg-brand)","$btn-brand-outline-active-bg":"var(--pgn-color-btn-active-bg-outline-brand)","$btn-brand-inverse-outline-active-bg":"var(--pgn-color-btn-active-bg-inverse-outline-brand)","$btn-brand-active-border-color":"var(--pgn-color-btn-active-border-brand)","$btn-brand-outline-active-border-color":"var(--pgn-color-btn-active-border-outline-brand)","$btn-brand-inverse-outline-active-border-color":"var(--pgn-color-btn-active-border-inverse-outline-brand)","$btn-brand-focus-border-color":"var(--pgn-color-btn-focus-border-brand)","$btn-brand-outline-focus-border-color":"var(--pgn-color-btn-focus-border-outline-brand)","$btn-brand-inverse-focus-border-color":"var(--pgn-color-btn-focus-border-inverse-brand)","$btn-brand-inverse-outline-focus-border-color":"var(--pgn-color-btn-focus-border-inverse-outline-brand)","$btn-padding-y":"var(--pgn-btn-padding-y-base)","$btn-padding-y-lg":"var(--pgn-btn-padding-y-lg)","$btn-padding-y-sm":"var(--pgn-btn-padding-y-sm)","$btn-padding-x":"var(--pgn-btn-padding-x-base)","$btn-padding-x-lg":"var(--pgn-btn-padding-x-lg)","$btn-padding-x-sm":"var(--pgn-btn-padding-x-sm)","$btn-font-family":"var(--pgn-btn-font-family)","$btn-font-size":"var(--pgn-btn-font-size-base)","$btn-font-size-sm":"var(--pgn-btn-font-size-sm)","$btn-font-size-lg":"var(--pgn-btn-font-size-lg)","$btn-font-weight":"var(--pgn-btn-font-weight)","$btn-line-height":"var(--pgn-btn-line-height-base)","$btn-line-height-sm":"var(--pgn-btn-line-height-sm)","$btn-line-height-lg":"var(--pgn-btn-line-height-lg)","$btn-border-width":"var(--pgn-btn-border-width)","$btn-border-radius":"var(--pgn-btn-border-radius-base)","$btn-border-radius-lg":"var(--pgn-btn-border-radius-lg)","$btn-border-radius-sm":"var(--pgn-btn-border-radius-sm)","$btn-box-shadow":"var(--pgn-btn-box-shadow-base)","$btn-active-box-shadow":"var(--pgn-btn-box-shadow-active)","$btn-focus-width":"var(--pgn-btn-focus-width)","$btn-focus-gap":"var(--pgn-btn-focus-gap)","$btn-disabled-opacity":"var(--pgn-btn-disabled-opacity)","$btn-link-disabled-color":"var(--pgn-btn-disabled-link-color)","$btn-block-spacing-y":"var(--pgn-btn-block-spacing-y)","$btn-transition":"var(--pgn-btn-transition)","$btn-danger-color":"var(--pgn-color-btn-text-danger)","$btn-danger-outline-color":"var(--pgn-color-btn-text-outline-danger)","$btn-danger-inverse-color":"var(--pgn-color-btn-text-inverse-danger)","$btn-danger-inverse-outline-color":"var(--pgn-color-btn-text-inverse-outline-danger)","$btn-danger-bg":"var(--pgn-color-btn-bg-danger)","$btn-danger-inverse-bg":"var(--pgn-color-btn-bg-inverse-danger)","$btn-danger-border-color":"var(--pgn-color-btn-border-danger)","$btn-danger-outline-border-color":"var(--pgn-color-btn-border-outline-danger)","$btn-danger-inverse-outline-border-color":"var(--pgn-color-btn-border-inverse-outline-danger)","$btn-danger-hover-color":"var(--pgn-color-btn-hover-text-danger)","$btn-danger-outline-hover-color":"var(--pgn-color-btn-hover-text-outline-danger)","$btn-danger-inverse-hover-color":"var(--pgn-color-btn-hover-text-inverse-danger)","$btn-danger-inverse-outline-hover-color":"var(--pgn-color-btn-hover-text-inverse-outline-danger)","$btn-danger-hover-bg":"var(--pgn-color-btn-hover-bg-danger)","$btn-danger-outline-hover-bg":"var(--pgn-color-btn-hover-bg-outline-danger)","$btn-danger-inverse-hover-bg":"var(--pgn-color-btn-hover-bg-inverse-danger)","$btn-danger-inverse-outline-hover-bg":"var(--pgn-color-btn-hover-bg-inverse-outline-danger)","$btn-danger-hover-border-color":"var(--pgn-color-btn-hover-border-danger)","$btn-danger-outline-hover-border-color":"var(--pgn-color-btn-hover-border-outline-danger)","$btn-danger-inverse-outline-hover-border-color":"var(--pgn-color-btn-hover-border-inverse-outline-danger)","$btn-danger-active-color":"var(--pgn-color-btn-active-text-danger)","$btn-danger-outline-active-color":"var(--pgn-color-btn-active-text-outline-danger)","$btn-danger-inverse-active-color":"var(--pgn-color-btn-active-text-inverse-danger)","$btn-danger-inverse-outline-active-color":"var(--pgn-color-btn-active-text-inverse-outline-danger)","$btn-danger-active-bg":"var(--pgn-color-btn-active-bg-danger)","$btn-danger-outline-active-bg":"var(--pgn-color-btn-active-bg-outline-danger)","$btn-danger-inverse-outline-active-bg":"var(--pgn-color-btn-active-bg-inverse-outline-danger)","$btn-danger-active-border-color":"var(--pgn-color-btn-active-border-danger)","$btn-danger-outline-active-border-color":"var(--pgn-color-btn-active-border-outline-danger)","$btn-danger-inverse-outline-active-border-color":"var(--pgn-color-btn-active-border-inverse-outline-danger)","$btn-danger-focus-border-color":"var(--pgn-color-btn-focus-border-danger)","$btn-danger-outline-focus-border-color":"var(--pgn-color-btn-focus-border-outline-danger)","$btn-danger-inverse-focus-border-color":"var(--pgn-color-btn-focus-border-inverse-danger)","$btn-danger-inverse-outline-focus-border-color":"var(--pgn-color-btn-focus-border-inverse-outline-danger)","$btn-dark-color":"var(--pgn-color-btn-text-dark)","$btn-dark-outline-color":"var(--pgn-color-btn-text-outline-dark)","$btn-dark-inverse-color":"var(--pgn-color-btn-text-inverse-dark)","$btn-dark-inverse-outline-color":"var(--pgn-color-btn-text-inverse-outline-dark)","$btn-dark-bg":"var(--pgn-color-btn-bg-dark)","$btn-dark-inverse-bg":"var(--pgn-color-btn-bg-inverse-dark)","$btn-dark-border-color":"var(--pgn-color-btn-border-dark)","$btn-dark-outline-border-color":"var(--pgn-color-btn-border-outline-dark)","$btn-dark-inverse-outline-border-color":"var(--pgn-color-btn-border-inverse-outline-dark)","$btn-dark-hover-color":"var(--pgn-color-btn-hover-text-dark)","$btn-dark-outline-hover-color":"var(--pgn-color-btn-hover-text-outline-dark)","$btn-dark-inverse-hover-color":"var(--pgn-color-btn-hover-text-inverse-dark)","$btn-dark-inverse-outline-hover-color":"var(--pgn-color-btn-hover-text-inverse-outline-dark)","$btn-dark-hover-bg":"var(--pgn-color-btn-hover-bg-dark)","$btn-dark-outline-hover-bg":"var(--pgn-color-btn-hover-bg-outline-dark)","$btn-dark-inverse-hover-bg":"var(--pgn-color-btn-hover-bg-inverse-dark)","$btn-dark-inverse-outline-hover-bg":"var(--pgn-color-btn-hover-bg-inverse-outline-dark)","$btn-dark-hover-border-color":"var(--pgn-color-btn-hover-border-dark)","$btn-dark-outline-hover-border-color":"var(--pgn-color-btn-hover-border-outline-dark)","$btn-dark-inverse-outline-hover-border-color":"var(--pgn-color-btn-hover-border-inverse-outline-dark)","$btn-dark-active-color":"var(--pgn-color-btn-active-text-dark)","$btn-dark-outline-active-color":"var(--pgn-color-btn-active-text-outline-dark)","$btn-dark-inverse-active-color":"var(--pgn-color-btn-active-text-inverse-dark)","$btn-dark-inverse-outline-active-color":"var(--pgn-color-btn-active-text-inverse-outline-dark)","$btn-dark-active-bg":"var(--pgn-color-btn-active-bg-dark)","$btn-dark-outline-active-bg":"var(--pgn-color-btn-active-bg-outline-dark)","$btn-dark-inverse-outline-active-bg":"var(--pgn-color-btn-active-bg-inverse-outline-dark)","$btn-dark-active-border-color":"var(--pgn-color-btn-active-border-dark)","$btn-dark-outline-active-border-color":"var(--pgn-color-btn-active-border-outline-dark)","$btn-dark-inverse-outline-active-border-color":"var(--pgn-color-btn-active-border-inverse-outline-dark)","$btn-dark-focus-border-color":"var(--pgn-color-btn-focus-border-dark)","$btn-dark-outline-focus-border-color":"var(--pgn-color-btn-focus-border-outline-dark)","$btn-dark-inverse-focus-border-color":"var(--pgn-color-btn-focus-border-inverse-dark)","$btn-dark-inverse-outline-focus-border-color":"var(--pgn-color-btn-focus-border-inverse-outline-dark)","$btn-info-color":"var(--pgn-color-btn-text-info)","$btn-info-outline-color":"var(--pgn-color-btn-text-outline-info)","$btn-info-inverse-color":"var(--pgn-color-btn-text-inverse-info)","$btn-info-inverse-outline-color":"var(--pgn-color-btn-text-inverse-outline-info)","$btn-info-bg":"var(--pgn-color-btn-bg-info)","$btn-info-inverse-bg":"var(--pgn-color-btn-bg-inverse-info)","$btn-info-border-color":"var(--pgn-color-btn-border-info)","$btn-info-outline-border-color":"var(--pgn-color-btn-border-outline-info)","$btn-info-inverse-outline-border-color":"var(--pgn-color-btn-border-inverse-outline-info)","$btn-info-hover-color":"var(--pgn-color-btn-hover-text-info)","$btn-info-outline-hover-color":"var(--pgn-color-btn-hover-text-outline-info)","$btn-info-inverse-hover-color":"var(--pgn-color-btn-hover-text-inverse-info)","$btn-info-inverse-outline-hover-color":"var(--pgn-color-btn-hover-text-inverse-outline-info)","$btn-info-hover-bg":"var(--pgn-color-btn-hover-bg-info)","$btn-info-outline-hover-bg":"var(--pgn-color-btn-hover-bg-outline-info)","$btn-info-inverse-hover-bg":"var(--pgn-color-btn-hover-bg-inverse-info)","$btn-info-inverse-outline-hover-bg":"var(--pgn-color-btn-hover-bg-inverse-outline-info)","$btn-info-hover-border-color":"var(--pgn-color-btn-hover-border-info)","$btn-info-outline-hover-border-color":"var(--pgn-color-btn-hover-border-outline-info)","$btn-info-inverse-outline-hover-border-color":"var(--pgn-color-btn-hover-border-inverse-outline-info)","$btn-info-active-color":"var(--pgn-color-btn-active-text-info)","$btn-info-outline-active-color":"var(--pgn-color-btn-active-text-outline-info)","$btn-info-inverse-active-color":"var(--pgn-color-btn-active-text-inverse-info)","$btn-info-inverse-outline-active-color":"var(--pgn-color-btn-active-text-inverse-outline-info)","$btn-info-active-bg":"var(--pgn-color-btn-active-bg-info)","$btn-info-outline-active-bg":"var(--pgn-color-btn-active-bg-outline-info)","$btn-info-inverse-outline-active-bg":"var(--pgn-color-btn-active-bg-inverse-outline-info)","$btn-info-active-border-color":"var(--pgn-color-btn-active-border-info)","$btn-info-outline-active-border-color":"var(--pgn-color-btn-active-border-outline-info)","$btn-info-inverse-outline-active-border-color":"var(--pgn-color-btn-active-border-inverse-outline-info)","$btn-info-focus-border-color":"var(--pgn-color-btn-focus-border-info)","$btn-info-outline-focus-border-color":"var(--pgn-color-btn-focus-border-outline-info)","$btn-info-inverse-focus-border-color":"var(--pgn-color-btn-focus-border-inverse-info)","$btn-info-inverse-outline-focus-border-color":"var(--pgn-color-btn-focus-border-inverse-outline-info)","$btn-light-color":"var(--pgn-color-btn-text-light)","$btn-light-outline-color":"var(--pgn-color-btn-text-outline-light)","$btn-light-inverse-color":"var(--pgn-color-btn-text-inverse-light)","$btn-light-inverse-outline-color":"var(--pgn-color-btn-text-inverse-outline-light)","$btn-light-bg":"var(--pgn-color-btn-bg-light)","$btn-light-inverse-bg":"var(--pgn-color-btn-bg-inverse-light)","$btn-light-border-color":"var(--pgn-color-btn-border-light)","$btn-light-outline-border-color":"var(--pgn-color-btn-border-outline-light)","$btn-light-inverse-outline-border-color":"var(--pgn-color-btn-border-inverse-outline-light)","$btn-light-hover-color":"var(--pgn-color-btn-hover-text-light)","$btn-light-outline-hover-color":"var(--pgn-color-btn-hover-text-outline-light)","$btn-light-inverse-hover-color":"var(--pgn-color-btn-hover-text-inverse-light)","$btn-light-inverse-outline-hover-color":"var(--pgn-color-btn-hover-text-inverse-outline-light)","$btn-light-hover-bg":"var(--pgn-color-btn-hover-bg-light)","$btn-light-outline-hover-bg":"var(--pgn-color-btn-hover-bg-outline-light)","$btn-light-inverse-hover-bg":"var(--pgn-color-btn-hover-bg-inverse-light)","$btn-light-inverse-outline-hover-bg":"var(--pgn-color-btn-hover-bg-inverse-outline-light)","$btn-light-hover-border-color":"var(--pgn-color-btn-hover-border-light)","$btn-light-outline-hover-border-color":"var(--pgn-color-btn-hover-border-outline-light)","$btn-light-inverse-outline-hover-border-color":"var(--pgn-color-btn-hover-border-inverse-outline-light)","$btn-light-active-color":"var(--pgn-color-btn-active-text-light)","$btn-light-outline-active-color":"var(--pgn-color-btn-active-text-outline-light)","$btn-light-inverse-active-color":"var(--pgn-color-btn-active-text-inverse-light)","$btn-light-inverse-outline-active-color":"var(--pgn-color-btn-active-text-inverse-outline-light)","$btn-light-active-bg":"var(--pgn-color-btn-active-bg-light)","$btn-light-outline-active-bg":"var(--pgn-color-btn-active-bg-outline-light)","$btn-light-inverse-outline-active-bg":"var(--pgn-color-btn-active-bg-inverse-outline-light)","$btn-light-active-border-color":"var(--pgn-color-btn-active-border-light)","$btn-light-outline-active-border-color":"var(--pgn-color-btn-active-border-outline-light)","$btn-light-inverse-outline-active-border-color":"var(--pgn-color-btn-active-border-inverse-outline-light)","$btn-light-focus-border-color":"var(--pgn-color-btn-focus-border-light)","$btn-light-outline-focus-border-color":"var(--pgn-color-btn-focus-border-outline-light)","$btn-light-inverse-focus-border-color":"var(--pgn-color-btn-focus-border-inverse-light)","$btn-light-inverse-outline-focus-border-color":"var(--pgn-color-btn-focus-border-inverse-outline-light)","$btn-primary-color":"var(--pgn-color-btn-text-primary)","$btn-primary-outline-color":"var(--pgn-color-btn-text-outline-primary)","$btn-primary-inverse-color":"var(--pgn-color-btn-text-inverse-primary)","$btn-primary-inverse-outline-color":"var(--pgn-color-btn-text-inverse-outline-primary)","$btn-primary-bg":"var(--pgn-color-btn-bg-primary)","$btn-primary-inverse-bg":"var(--pgn-color-btn-bg-inverse-primary)","$btn-primary-border-color":"var(--pgn-color-btn-border-primary)","$btn-primary-outline-border-color":"var(--pgn-color-btn-border-outline-primary)","$btn-primary-inverse-outline-border-color":"var(--pgn-color-btn-border-inverse-outline-primary)","$btn-primary-hover-color":"var(--pgn-color-btn-hover-text-primary)","$btn-primary-outline-hover-color":"var(--pgn-color-btn-hover-text-outline-primary)","$btn-primary-inverse-hover-color":"var(--pgn-color-btn-hover-text-inverse-primary)","$btn-primary-inverse-outline-hover-color":"var(--pgn-color-btn-hover-text-inverse-outline-primary)","$btn-primary-hover-bg":"var(--pgn-color-btn-hover-bg-primary)","$btn-primary-outline-hover-bg":"var(--pgn-color-btn-hover-bg-outline-primary)","$btn-primary-inverse-hover-bg":"var(--pgn-color-btn-hover-bg-inverse-primary)","$btn-primary-inverse-outline-hover-bg":"var(--pgn-color-btn-hover-bg-inverse-outline-primary)","$btn-primary-hover-border-color":"var(--pgn-color-btn-hover-border-primary)","$btn-primary-outline-hover-border-color":"var(--pgn-color-btn-hover-border-outline-primary)","$btn-primary-inverse-outline-hover-border-color":"var(--pgn-color-btn-hover-border-inverse-outline-primary)","$btn-primary-active-color":"var(--pgn-color-btn-active-text-primary)","$btn-primary-outline-active-color":"var(--pgn-color-btn-active-text-outline-primary)","$btn-primary-inverse-active-color":"var(--pgn-color-btn-active-text-inverse-primary)","$btn-primary-inverse-outline-active-color":"var(--pgn-color-btn-active-text-inverse-outline-primary)","$btn-primary-active-bg":"var(--pgn-color-btn-active-bg-primary)","$btn-primary-outline-active-bg":"var(--pgn-color-btn-active-bg-outline-primary)","$btn-primary-inverse-outline-active-bg":"var(--pgn-color-btn-active-bg-inverse-outline-primary)","$btn-primary-active-border-color":"var(--pgn-color-btn-active-border-primary)","$btn-primary-outline-active-border-color":"var(--pgn-color-btn-active-border-outline-primary)","$btn-primary-inverse-outline-active-border-color":"var(--pgn-color-btn-active-border-inverse-outline-primary)","$btn-primary-focus-border-color":"var(--pgn-color-btn-focus-border-primary)","$btn-primary-outline-focus-border-color":"var(--pgn-color-btn-focus-border-outline-primary)","$btn-primary-inverse-focus-border-color":"var(--pgn-color-btn-focus-border-inverse-primary)","$btn-primary-inverse-outline-focus-border-color":"var(--pgn-color-btn-focus-border-inverse-outline-primary)","$btn-secondary-color":"var(--pgn-color-btn-text-secondary)","$btn-secondary-outline-color":"var(--pgn-color-btn-text-outline-secondary)","$btn-secondary-inverse-color":"var(--pgn-color-btn-text-inverse-secondary)","$btn-secondary-inverse-outline-color":"var(--pgn-color-btn-text-inverse-outline-secondary)","$btn-secondary-bg":"var(--pgn-color-btn-bg-secondary)","$btn-secondary-inverse-bg":"var(--pgn-color-btn-bg-inverse-secondary)","$btn-secondary-border-color":"var(--pgn-color-btn-border-secondary)","$btn-secondary-outline-border-color":"var(--pgn-color-btn-border-outline-secondary)","$btn-secondary-inverse-outline-border-color":"var(--pgn-color-btn-border-inverse-outline-secondary)","$btn-secondary-hover-color":"var(--pgn-color-btn-hover-text-secondary)","$btn-secondary-outline-hover-color":"var(--pgn-color-btn-hover-text-outline-secondary)","$btn-secondary-inverse-hover-color":"var(--pgn-color-btn-hover-text-inverse-secondary)","$btn-secondary-inverse-outline-hover-color":"var(--pgn-color-btn-hover-text-inverse-outline-secondary)","$btn-secondary-hover-bg":"var(--pgn-color-btn-hover-bg-secondary)","$btn-secondary-outline-hover-bg":"var(--pgn-color-btn-hover-bg-outline-secondary)","$btn-secondary-inverse-hover-bg":"var(--pgn-color-btn-hover-bg-inverse-secondary)","$btn-secondary-inverse-outline-hover-bg":"var(--pgn-color-btn-hover-bg-inverse-outline-secondary)","$btn-secondary-hover-border-color":"var(--pgn-color-btn-hover-border-secondary)","$btn-secondary-outline-hover-border-color":"var(--pgn-color-btn-hover-border-outline-secondary)","$btn-secondary-inverse-outline-hover-border-color":"var(--pgn-color-btn-hover-border-inverse-outline-secondary)","$btn-secondary-active-color":"var(--pgn-color-btn-active-text-secondary)","$btn-secondary-outline-active-color":"var(--pgn-color-btn-active-text-outline-secondary)","$btn-secondary-inverse-active-color":"var(--pgn-color-btn-active-text-inverse-secondary)","$btn-secondary-inverse-outline-active-color":"var(--pgn-color-btn-active-text-inverse-outline-secondary)","$btn-secondary-active-bg":"var(--pgn-color-btn-active-bg-secondary)","$btn-secondary-outline-active-bg":"var(--pgn-color-btn-active-bg-outline-secondary)","$btn-secondary-inverse-outline-active-bg":"var(--pgn-color-btn-active-bg-inverse-outline-secondary)","$btn-secondary-active-border-color":"var(--pgn-color-btn-active-border-secondary)","$btn-secondary-outline-active-border-color":"var(--pgn-color-btn-active-border-outline-secondary)","$btn-secondary-inverse-outline-active-border-color":"var(--pgn-color-btn-active-border-inverse-outline-secondary)","$btn-secondary-focus-border-color":"var(--pgn-color-btn-focus-border-secondary)","$btn-secondary-outline-focus-border-color":"var(--pgn-color-btn-focus-border-outline-secondary)","$btn-secondary-inverse-focus-border-color":"var(--pgn-color-btn-focus-border-inverse-secondary)","$btn-secondary-inverse-outline-focus-border-color":"var(--pgn-color-btn-focus-border-inverse-outline-secondary)","$btn-success-color":"var(--pgn-color-btn-text-success)","$btn-success-outline-color":"var(--pgn-color-btn-text-outline-success)","$btn-success-inverse-color":"var(--pgn-color-btn-text-inverse-success)","$btn-success-inverse-outline-color":"var(--pgn-color-btn-text-inverse-outline-success)","$btn-success-bg":"var(--pgn-color-btn-bg-success)","$btn-success-inverse-bg":"var(--pgn-color-btn-bg-inverse-success)","$btn-success-border-color":"var(--pgn-color-btn-border-success)","$btn-success-outline-border-color":"var(--pgn-color-btn-border-outline-success)","$btn-success-inverse-outline-border-color":"var(--pgn-color-btn-border-inverse-outline-success)","$btn-success-hover-color":"var(--pgn-color-btn-hover-text-success)","$btn-success-outline-hover-color":"var(--pgn-color-btn-hover-text-outline-success)","$btn-success-inverse-hover-color":"var(--pgn-color-btn-hover-text-inverse-success)","$btn-success-inverse-outline-hover-color":"var(--pgn-color-btn-hover-text-inverse-outline-success)","$btn-success-hover-bg":"var(--pgn-color-btn-hover-bg-success)","$btn-success-outline-hover-bg":"var(--pgn-color-btn-hover-bg-outline-success)","$btn-success-inverse-hover-bg":"var(--pgn-color-btn-hover-bg-inverse-success)","$btn-success-inverse-outline-hover-bg":"var(--pgn-color-btn-hover-bg-inverse-outline-success)","$btn-success-hover-border-color":"var(--pgn-color-btn-hover-border-success)","$btn-success-outline-hover-border-color":"var(--pgn-color-btn-hover-border-outline-success)","$btn-success-inverse-outline-hover-border-color":"var(--pgn-color-btn-hover-border-inverse-outline-success)","$btn-success-active-color":"var(--pgn-color-btn-active-text-success)","$btn-success-outline-active-color":"var(--pgn-color-btn-active-text-outline-success)","$btn-success-inverse-active-color":"var(--pgn-color-btn-active-text-inverse-success)","$btn-success-inverse-outline-active-color":"var(--pgn-color-btn-active-text-inverse-outline-success)","$btn-success-active-bg":"var(--pgn-color-btn-active-bg-success)","$btn-success-outline-active-bg":"var(--pgn-color-btn-active-bg-outline-success)","$btn-success-inverse-outline-active-bg":"var(--pgn-color-btn-active-bg-inverse-outline-success)","$btn-success-active-border-color":"var(--pgn-color-btn-active-border-success)","$btn-success-outline-active-border-color":"var(--pgn-color-btn-active-border-outline-success)","$btn-success-inverse-outline-active-border-color":"var(--pgn-color-btn-active-border-inverse-outline-success)","$btn-success-focus-border-color":"var(--pgn-color-btn-focus-border-success)","$btn-success-outline-focus-border-color":"var(--pgn-color-btn-focus-border-outline-success)","$btn-success-inverse-focus-border-color":"var(--pgn-color-btn-focus-border-inverse-success)","$btn-success-inverse-outline-focus-border-color":"var(--pgn-color-btn-focus-border-inverse-outline-success)","$btn-tertiary-color":"var(--pgn-color-btn-text-tertiary)","$btn-inverse-tertiary-color":"var(--pgn-color-btn-text-inverse-tertiary)","$btn-tertiary-bg":"var(--pgn-color-btn-bg-tertiary)","$btn-inverse-tertiary-bg":"var(--pgn-color-btn-bg-inverse-tertiary)","$btn-tertiary-border-color":"var(--pgn-color-btn-border-tertiary)","$btn-inverse-tertiary-border-color":"var(--pgn-color-btn-border-inverse-tertiary)","$btn-tertiary-hover-color":"var(--pgn-color-btn-hover-text-tertiary)","$btn-inverse-tertiary-hover-color":"var(--pgn-color-btn-hover-text-inverse-tertiary)","$btn-tertiary-hover-bg":"var(--pgn-color-btn-hover-bg-tertiary)","$btn-inverse-tertiary-hover-bg":"var(--pgn-color-btn-hover-bg-inverse-tertiary)","$btn-tertiary-hover-border-color":"var(--pgn-color-btn-hover-border-tertiary)","$btn-inverse-tertiary-hover-border-color":"var(--pgn-color-btn-hover-border-inverse-tertiary)","$btn-tertiary-active-color":"var(--pgn-color-btn-active-text-tertiary)","$btn-inverse-tertiary-active-color":"var(--pgn-color-btn-active-text-inverse-tertiary)","$btn-tertiary-active-bg":"var(--pgn-color-btn-active-bg-tertiary)","$btn-inverse-tertiary-active-bg":"var(--pgn-color-btn-active-bg-inverse-tertiary)","$btn-tertiary-active-border-color":"var(--pgn-color-btn-active-border-tertiary)","$btn-inverse-tertiary-active-border-color":"var(--pgn-color-btn-active-border-inverse-tertiary)","$btn-tertiary-focus-border-color":"var(--pgn-color-btn-focus-border-tertiary)","$btn-tertiary-inverse-focus-border-color":"var(--pgn-color-btn-focus-border-inverse-tertiary)","$btn-warning-color":"var(--pgn-color-btn-text-warning)","$btn-warning-outline-color":"var(--pgn-color-btn-text-outline-warning)","$btn-warning-inverse-color":"var(--pgn-color-btn-text-inverse-warning)","$btn-warning-inverse-outline-color":"var(--pgn-color-btn-text-inverse-outline-warning)","$btn-warning-bg":"var(--pgn-color-btn-bg-warning)","$btn-warning-inverse-bg":"var(--pgn-color-btn-bg-inverse-warning)","$btn-warning-border-color":"var(--pgn-color-btn-border-warning)","$btn-warning-outline-border-color":"var(--pgn-color-btn-border-outline-warning)","$btn-warning-inverse-outline-border-color":"var(--pgn-color-btn-border-inverse-outline-warning)","$btn-warning-hover-color":"var(--pgn-color-btn-hover-text-warning)","$btn-warning-outline-hover-color":"var(--pgn-color-btn-hover-text-outline-warning)","$btn-warning-inverse-hover-color":"var(--pgn-color-btn-hover-text-inverse-warning)","$btn-warning-inverse-outline-hover-color":"var(--pgn-color-btn-hover-text-inverse-outline-warning)","$btn-warning-hover-bg":"var(--pgn-color-btn-hover-bg-warning)","$btn-warning-outline-hover-bg":"var(--pgn-color-btn-hover-bg-outline-warning)","$btn-warning-inverse-hover-bg":"var(--pgn-color-btn-hover-bg-inverse-warning)","$btn-warning-inverse-outline-hover-bg":"var(--pgn-color-btn-hover-bg-inverse-outline-warning)","$btn-warning-hover-border-color":"var(--pgn-color-btn-hover-border-warning)","$btn-warning-outline-hover-border-color":"var(--pgn-color-btn-hover-border-outline-warning)","$btn-warning-inverse-outline-hover-border-color":"var(--pgn-color-btn-hover-border-inverse-outline-warning)","$btn-warning-active-color":"var(--pgn-color-btn-active-text-warning)","$btn-warning-outline-active-color":"var(--pgn-color-btn-active-text-outline-warning)","$btn-warning-inverse-active-color":"var(--pgn-color-btn-active-text-inverse-warning)","$btn-warning-inverse-outline-active-color":"var(--pgn-color-btn-active-text-inverse-outline-warning)","$btn-warning-active-bg":"var(--pgn-color-btn-active-bg-warning)","$btn-warning-outline-active-bg":"var(--pgn-color-btn-active-bg-outline-warning)","$btn-warning-inverse-outline-active-bg":"var(--pgn-color-btn-active-bg-inverse-outline-warning)","$btn-warning-active-border-color":"var(--pgn-color-btn-active-border-warning)","$btn-warning-outline-active-border-color":"var(--pgn-color-btn-active-border-outline-warning)","$btn-warning-inverse-outline-active-border-color":"var(--pgn-color-btn-active-border-inverse-outline-warning)","$btn-warning-focus-border-color":"var(--pgn-color-btn-focus-border-warning)","$btn-warning-outline-focus-border-color":"var(--pgn-color-btn-focus-border-outline-warning)","$btn-warning-inverse-focus-border-color":"var(--pgn-color-btn-focus-border-inverse-warning)","$btn-warning-inverse-outline-focus-border-color":"var(--pgn-color-btn-focus-border-inverse-outline-warning)","$card-color":"var(--pgn-color-card-base)","$card-bg":"var(--pgn-color-card-bg)","$card-border-color":"var(--pgn-color-card-border-base)","$card-border-focus-color":"var(--pgn-color-card-border-focus)","$card-divider-bg":"var(--pgn-color-card-divider-bg)","$card-spacer-x":"var(--pgn-spacing-card-spacer-x)","$card-spacer-y":"var(--pgn-spacing-card-spacer-y)","$card-group-margin":"var(--pgn-spacing-card-margin-group)","$card-deck-margin":"var(--pgn-spacing-card-margin-deck)","$card-grid-margin":"var(--pgn-spacing-card-margin-grid)","$card-columns-margin":"var(--pgn-spacing-card-columns-margin)","$card-columns-count":"var(--pgn-spacing-card-columns-count)","$card-columns-gap":"var(--pgn-spacing-card-columns-gap)","$card-footer-actions-gap":"var(--pgn-spacing-card-footer-action-gap)","$loading-skeleton-spacer":"var(--pgn-spacing-card-loading-skeleton-spacer)","$card-logo-left-offset":"var(--pgn-spacing-card-logo-left-offset-base)","$card-logo-left-offset-horizontal":"var(--pgn-spacing-card-logo-left-offset-horizontal)","$card-logo-bottom-offset":"var(--pgn-spacing-card-logo-bottom-offset-base)","$card-logo-bottom-offset-horizontal":"var(--pgn-spacing-card-logo-bottom-offset-horizontal)","$card-border-width":"var(--pgn-size-card-border-width)","$card-border-radius":"var(--pgn-size-card-border-radius-base)","$card-image-border-radius":"var(--pgn-size-card-border-radius-image)","$card-logo-border-radius":"var(--pgn-size-card-border-radius-logo)","$card-image-horizontal-max-width":"var(--pgn-size-card-image-horizontal-width-max)","$card-image-horizontal-min-width":"var(--pgn-size-card-image-horizontal-width-min)","$card-image-vertical-max-height":"var(--pgn-size-card-image-vertical-max-height)","$card-logo-width":"var(--pgn-size-card-logo-width)","$card-logo-height":"var(--pgn-size-card-logo-height)","$card-footer-text-font-size":"var(--pgn-typography-footer-text-font-size)","$carousel-control-color":"var(--pgn-color-carousel-control-base)","$carousel-control-opacity":"var(--pgn-color-carousel-control-opacity-base)","$carousel-control-hover-opacity":"var(--pgn-color-carousel-control-opacity-hover)","$carousel-indicator-active-bg":"var(--pgn-color-carousel-indicator-active-bg)","$carousel-caption-color":"var(--pgn-color-carousel-caption)","$carousel-control-width":"var(--pgn-size-carousel-control-width-base)","$carousel-control-icon-width":"var(--pgn-size-carousel-control-width-icon)","$carousel-indicator-width":"var(--pgn-size-carousel-indicator-width)","$carousel-indicator-height":"var(--pgn-size-carousel-indicator-height-base)","$carousel-indicator-hit-area-height":"var(--pgn-size-carousel-indicator-height-area-hit)","$carousel-caption-width":"var(--pgn-size-carousel-caption-width)","$carousel-indicator-spacer":"var(--pgn-spacing-carousel-indicator-spacer)","$carousel-transition-duration":"var(--pgn-transition-carousel-duration)","$carousel-indicator-transition":"var(--pgn-transition-carousel-indicator)","$carousel-control-transition":"var(--pgn-transition-carousel-control)","$carousel-control-prev-icon-bg":"var(--pgn-content-carousel-control-bg-prev-icon)","$carousel-control-next-icon-bg":"var(--pgn-content-carousel-control-bg-next-icon)","$chip-light-color":"var(--pgn-color-chip-text-light)","$chip-dark-color":"var(--pgn-color-chip-text-dark)","$chip-light-bg":"var(--pgn-color-chip-bg-light)","$chip-dark-bg":"var(--pgn-color-chip-bg-dark)","$chip-disable-opacity":"var(--pgn-color-chip-opacity-disabled)","$chip-margin":"var(--pgn-spacing-chip-margin)","$chip-padding-y":"var(--pgn-spacing-chip-padding-y)","$chip-padding-x":"var(--pgn-spacing-chip-padding-x)","$chip-icon-padding":"var(--pgn-spacing-chip-padding-icon)","$chip-padding-to-icon":"var(--pgn-spacing-chip-padding-to-icon)","$chip-border-radius":"var(--pgn-size-chip-border-radius)","$chip-icon-size":"var(--pgn-size-chip-icon)","$close-color":"var(--pgn-color-close-button)","$close-font-size":"var(--pgn-typography-close-button-font-size)","$close-font-weight":"var(--pgn-typography-close-button-font-weight)","$close-text-shadow":"var(--pgn-elevation-close-button-text-shadow)","$code-color":"var(--pgn-color-code-base)","$kbd-color":"var(--pgn-color-code-kbd-base)","$kbd-bg":"var(--pgn-color-code-kbd-bg)","$pre-color":"var(--pgn-color-code-pre)","$code-font-size":"var(--pgn-typography-code-font-size)","$kbd-font-size":"var(--pgn-typography-code-kbd-font-size)","$nested-kbd-font-weight":"var(--pgn-typography-code-kbd-nested-font-weight)","$kbd-padding-y":"var(--pgn-spacing-code-kbd-padding-y)","$kbd-padding-x":"var(--pgn-spacing-code-kbd-padding-x)","$pre-scrollable-max-height":"var(--pgn-size-code-pre-scrollable-max-height)","$kbd-box-shadow":"var(--pgn-elevation-code-kbd-box-shadow)","$collapsible-card-spacer-y":"var(--pgn-spacing-collapsible-card-spacer-y-base)","$collapsible-card-spacer-y-lg":"var(--pgn-spacing-collapsible-card-spacer-y-lg)","$collapsible-card-spacer-x":"var(--pgn-spacing-collapsible-card-spacer-x-base)","$collapsible-card-spacer-x-lg":"var(--pgn-spacing-collapsible-card-spacer-x-lg)","$collapsible-card-body-spacer-left":"var(--pgn-spacing-collapsible-card-spacer-left-body)","$collapsible-card-spacer-icon":"var(--pgn-spacing-collapsible-card-spacer-icon)","$collapsible-basic-spacer-y":"var(--pgn-spacing-collapsible-card-spacer-basic-y)","$collapsible-basic-spacer-x":"var(--pgn-spacing-collapsible-card-spacer-basic-x)","$collapsible-basic-spacer-icon":"var(--pgn-spacing-collapsible-card-spacer-basic-icon)","$max-width-xs":"var(--pgn-size-container-max-width-xs)","$max-width-sm":"var(--pgn-size-container-max-width-sm)","$max-width-md":"var(--pgn-size-container-max-width-md)","$max-width-lg":"var(--pgn-size-container-max-width-lg)","$max-width-xl":"var(--pgn-size-container-max-width-xl)","$data-table-background-color":"var(--pgn-color-data-table-bg-base)","$data-table-is-loading-bg":"var(--pgn-color-data-table-bg-is-loading)","$data-table-border-color":"var(--pgn-color-data-table-border)","$data-table-box-shadow":"var(--pgn-elevation-data-table-box-shadow)","$data-table-border":"var(--pgn-size-data-table-border)","$data-table-pagination-dropdown-max-height":"var(--pgn-size-data-table-dropdown-pagination-max-height)","$data-table-pagination-dropdown-min-width":"var(--pgn-size-data-table-dropdown-pagination-min-width)","$data-table-padding-x":"var(--pgn-spacing-data-table-padding-x)","$data-table-padding-y":"var(--pgn-spacing-data-table-padding-y)","$data-table-padding-small":"var(--pgn-spacing-data-table-padding-small)","$data-table-cell-padding":"var(--pgn-spacing-data-table-padding-cell)","$data-table-head-cell-padding":"var(--pgn-spacing-data-table-padding-head-cell)","$data-table-footer-position":"var(--pgn-spacing-data-table-footer-position)","$dropdown-color":"var(--pgn-color-dropdown-text)","$dropdown-header-color":"var(--pgn-color-dropdown-header)","$dropdown-bg":"var(--pgn-color-dropdown-bg)","$dropdown-border-color":"var(--pgn-color-dropdown-border)","$dropdown-divider-bg":"var(--pgn-color-dropdown-divider-bg)","$dropdown-link-color":"var(--pgn-color-dropdown-link-base)","$dropdown-link-hover-color":"var(--pgn-color-dropdown-link-hover-base)","$dropdown-link-hover-bg":"var(--pgn-color-dropdown-link-hover-bg)","$dropdown-link-active-color":"var(--pgn-color-dropdown-link-active-base)","$dropdown-link-active-bg":"var(--pgn-color-dropdown-link-active-bg)","$dropdown-link-disabled-color":"var(--pgn-color-dropdown-link-disabled)","$dropdown-font-size":"var(--pgn-typography-dropdown-font-size)","$dropdown-min-width":"var(--pgn-size-dropdown-min-width)","$dropdown-border-width":"var(--pgn-size-dropdown-border-width)","$dropdown-border-radius":"var(--pgn-size-dropdown-border-radius-base)","$dropdown-inner-border-radius":"var(--pgn-size-dropdown-border-radius-inner)","$dropdown-spacer":"var(--pgn-spacing-dropdown-spacer)","$dropdown-padding-x":"var(--pgn-spacing-dropdown-padding-x-base)","$dropdown-item-padding-x":"var(--pgn-spacing-dropdown-padding-x-item)","$dropdown-padding-y":"var(--pgn-spacing-dropdown-padding-y-base)","$dropdown-item-padding-y":"var(--pgn-spacing-dropdown-padding-y-item)","$dropdown-header-padding":"var(--pgn-spacing-dropdown-padding-header)","$dropdown-divider-margin-y":"var(--pgn-spacing-dropdown-divider-margin-y)","$modal-close-container-top":"var(--pgn-spacing-dropdown-close-container-top)","$dropdown-box-shadow":"var(--pgn-elevation-dropdown-box-shadow)","$zindex-dropdown":"var(--pgn-elevation-dropdown-zindex)","$dropzone-error-wrapper-color":"var(--pgn-color-dropzone-error-wrapper)","$dropzone-restriction-msg-color":"var(--pgn-color-dropzone-restriction-msg)","$dropzone-border-color-default":"var(--pgn-color-dropzone-border-base)","$dropzone-border-color-hover":"var(--pgn-color-dropzone-border-hover)","$dropzone-border-color-focus":"var(--pgn-color-dropzone-border-focus)","$dropzone-border-color-active":"var(--pgn-color-dropzone-border-active)","$dropzone-border-color-error":"var(--pgn-color-dropzone-border-error)","$dropzone-restriction-msg-font-size":"var(--pgn-typography-dropzone-restriction-msg-font-size)","$dropzone-padding":"var(--pgn-spacing-dropzone-padding)","$dropzone-border-default":"var(--pgn-spacing-dropzone-border-base)","$dropzone-border-hover":"var(--pgn-spacing-dropzone-border-hover)","$dropzone-border-focus":"var(--pgn-spacing-dropzone-border-focus)","$dropzone-border-active":"var(--pgn-spacing-dropzone-border-active)","$dropzone-border-error":"var(--pgn-spacing-dropzone-border-error)","$input-color":"var(--pgn-color-form-input-base)","$input-placeholder-color":"var(--pgn-color-form-input-plaintext)","$input-border-color":"var(--pgn-color-form-input-border)","$input-bg":"var(--pgn-color-form-input-bg-base)","$input-disabled-bg":"var(--pgn-color-form-input-bg-disabled)","$input-group-addon-color":"var(--pgn-color-form-input-group-addon-base)","$input-group-addon-border-color":"var(--pgn-color-form-input-group-addon-border)","$input-group-addon-bg":"var(--pgn-color-form-input-group-addon-bg)","$input-focus-color":"var(--pgn-color-form-input-focus-base)","$input-focus-border-color":"var(--pgn-color-form-input-focus-border)","$input-focus-bg":"var(--pgn-color-form-input-focus-bg)","$custom-control-indicator-border-color":"var(--pgn-color-form-control-indicator-border)","$custom-control-indicator-bg":"var(--pgn-color-form-control-indicator-bg-base)","$custom-control-indicator-disabled-bg":"var(--pgn-color-form-control-indicator-bg-disabled)","$custom-control-indicator-checked-color":"var(--pgn-color-form-control-indicator-checked-base)","$custom-control-indicator-checked-bg":"var(--pgn-color-form-control-indicator-checked-bg-base)","$custom-control-indicator-checked-disabled-bg":"var(--pgn-color-form-control-indicator-checked-bg-disabled)","$custom-control-indicator-checked-border-color":"var(--pgn-color-form-control-indicator-checked-border-base)","$custom-control-indicator-focus-border-color":"var(--pgn-color-form-control-indicator-checked-border-focus)","$custom-control-indicator-active-color":"var(--pgn-color-form-control-indicator-active-base)","$custom-control-indicator-active-bg":"var(--pgn-color-form-control-indicator-active-bg)","$custom-control-indicator-active-border-color":"var(--pgn-color-form-control-indicator-active-border)","$custom-control-label-color":"var(--pgn-color-form-control-label-base)","$custom-control-label-disabled-color":"var(--pgn-color-form-control-label-disabled)","$form-control-floating-label-text-bg":"var(--pgn-color-form-control-label-floating-text)","$custom-checkbox-indicator-indeterminate-color":"var(--pgn-color-form-control-checkbox-indicator-indeterminate-base)","$custom-checkbox-indicator-indeterminate-bg":"var(--pgn-color-form-control-checkbox-indicator-indeterminate-bg)","$custom-checkbox-indicator-indeterminate-border-color":"var(--pgn-color-form-control-checkbox-indicator-indeterminate-border)","$custom-switch-indicator-checked-bg":"var(--pgn-color-form-control-switch-indicator-checked-bg)","$custom-select-color":"var(--pgn-color-form-control-select-base)","$custom-select-disabled-color":"var(--pgn-color-form-control-select-disabled)","$custom-select-indicator-color":"var(--pgn-color-form-control-select-indicator-base)","$custom-select-bg":"var(--pgn-color-form-control-select-bg-base)","$custom-select-disabled-bg":"var(--pgn-color-form-control-select-bg-disabled)","$custom-select-bg-size":"var(--pgn-color-form-control-select-bg-size)","$custom-select-border-color":"var(--pgn-color-form-control-select-border-base)","$custom-select-focus-border-color":"var(--pgn-color-form-control-select-border-focus)","$custom-range-track-bg":"var(--pgn-color-form-control-range-track-bg)","$custom-range-thumb-bg":"var(--pgn-color-form-control-range-thumb-bg-base)","$custom-range-thumb-disabled-bg":"var(--pgn-color-form-control-range-thumb-bg-disabled)","$custom-range-thumb-active-bg":"var(--pgn-color-form-control-range-thumb-bg-active)","$custom-file-color":"var(--pgn-color-form-control-file-base)","$custom-file-bg":"var(--pgn-color-form-control-file-bg-base)","$custom-file-disabled-bg":"var(--pgn-color-form-control-file-bg-disabled)","$custom-file-button-color":"var(--pgn-color-form-control-file-button-base)","$custom-file-button-bg":"var(--pgn-color-form-control-file-button-bg)","$custom-file-border-color":"var(--pgn-color-form-control-file-border-base)","$custom-file-focus-border-color":"var(--pgn-color-form-control-file-border-focus)","$form-feedback-valid-color":"var(--pgn-color-form-feedback-valid)","$form-feedback-invalid-color":"var(--pgn-color-form-feedback-invalid)","$form-feedback-icon-valid-color":"var(--pgn-color-form-feedback-icon-valid)","$form-feedback-icon-invalid-color":"var(--pgn-color-form-feedback-icon-invalid)","$form-feedback-tooltip-valid-color":"var(--pgn-color-form-feedback-tooltip-valid)","$form-feedback-tooltip-invalid-color":"var(--pgn-color-form-feedback-tooltip-invalid)","$form-feedback-tooltip-valid-bg":"var(--pgn-color-form-feedback-tooltip-bg-valid)","$form-feedback-tooltip-invalid-bg":"var(--pgn-color-form-feedback-tooltip-bg-invalid)","$form-feedback-focus-box-shadow-valid-color":"var(--pgn-color-form-feedback-tooltip-box-shadow-focus-valid)","$form-feedback-focus-box-shadow-invalid-color":"var(--pgn-color-form-feedback-tooltip-box-shadow-focus-invalid)","$form-feedback-tooltip-opacity":"var(--pgn-color-form-feedback-tooltip-opacity)","$form-feedback-checked-valid-color":"var(--pgn-color-form-feedback-checked-valid)","$form-feedback-checked-invalid-color":"var(--pgn-color-form-feedback-checked-invalid)","$input-box-shadow":"var(--pgn-elevation-form-input-base)","$input-focus-box-shadow":"var(--pgn-elevation-form-input-focus)","$custom-control-indicator-box-shadow":"var(--pgn-elevation-form-control-indicator-base)","$custom-control-indicator-checked-box-shadow":"var(--pgn-elevation-form-control-indicator-checked-base)","$custom-control-indicator-focus-box-shadow":"var(--pgn-elevation-form-control-indicator-checked-focus)","$custom-control-indicator-active-box-shadow":"var(--pgn-elevation-form-control-indicator-active)","$custom-checkbox-indicator-indeterminate-box-shadow":"var(--pgn-elevation-form-control-checkbox-indicator-indeterminate)","$custom-range-track-box-shadow":"var(--pgn-elevation-form-control-range-track)","$custom-range-thumb-box-shadow":"var(--pgn-elevation-form-control-range-thumb-base)","$custom-range-thumb-focus-box-shadow":"var(--pgn-elevation-form-control-range-thumb-focus)","$custom-file-box-shadow":"var(--pgn-elevation-form-control-file-base)","$custom-file-focus-box-shadow":"var(--pgn-elevation-form-control-file-focus)","$custom-select-box-shadow":"var(--pgn-elevation-form-control-select-border-base)","$custom-select-focus-box-shadow":"var(--pgn-elevation-form-control-select-border-focus)","$custom-control-cursor":"var(--pgn-other-form-control-cursor)","$custom-range-track-cursor":"var(--pgn-other-form-control-range-track-cursor)","$custom-checkbox-indicator-icon-checked":"var(--pgn-other-content-form-control-checkbox-indicator-icon-checked)","$custom-checkbox-indicator-icon-indeterminate":"var(--pgn-other-content-form-control-checkbox-indicator-indeterminate-icon)","$custom-radio-indicator-icon-checked":"var(--pgn-other-content-form-control-radio-indicator-icon-checked)","$custom-switch-indicator-icon-off":"var(--pgn-other-content-form-control-switch-indicator-icon-off)","$custom-switch-indicator-icon-on":"var(--pgn-other-content-form-control-switch-indicator-icon-on)","$custom-select-indicator":"var(--pgn-other-content-form-control-select-indicator-icon)","$form-feedback-icon-valid":"var(--pgn-other-content-form-feedback-icon-valid)","$form-feedback-icon-invalid":"var(--pgn-other-content-form-feedback-icon-invalid)","$input-height":"var(--pgn-size-form-input-height-base)","$input-height-sm":"var(--pgn-size-form-input-height-sm)","$input-height-lg":"var(--pgn-size-form-input-height-lg)","$input-height-inner":"var(--pgn-size-form-input-height-inner-base)","$input-height-inner-half":"var(--pgn-size-form-input-height-inner-half)","$input-height-inner-quarter":"var(--pgn-size-form-input-height-inner-quarter)","$input-height-border":"var(--pgn-size-form-input-height-border)","$input-hover-width":"var(--pgn-size-form-input-width-hover)","$input-focus-width":"var(--pgn-size-form-input-width-focus)","$input-border-width":"var(--pgn-size-form-input-width-border)","$input-border-radius":"var(--pgn-size-form-input-radius-border-base)","$input-border-radius-lg":"var(--pgn-size-form-input-radius-border-lg)","$input-border-radius-sm":"var(--pgn-size-form-input-radius-border-sm)","$custom-control-indicator-size":"var(--pgn-size-form-control-indicator-base)","$custom-control-indicator-bg-size":"var(--pgn-size-form-control-indicator-bg)","$custom-control-indicator-border-width":"var(--pgn-size-form-control-indicator-border-width)","$custom-switch-width":"var(--pgn-size-form-control-switch-width)","$custom-switch-indicator-size":"var(--pgn-size-form-control-switch-indicator-base)","$custom-switch-indicator-border-radius":"var(--pgn-size-form-control-switch-indicator-border-radius)","$custom-select-height":"var(--pgn-size-form-control-select-height-base)","$custom-select-height-lg":"var(--pgn-size-form-control-select-height-lg)","$custom-select-height-sm":"var(--pgn-size-form-control-select-height-sm)","$custom-select-feedback-icon-size":"var(--pgn-size-form-control-select-feedback-icon)","$custom-select-border-width":"var(--pgn-size-form-control-select-border-width-base)","$custom-select-focus-width":"var(--pgn-size-form-control-select-border-width-focus)","$custom-select-border-radius":"var(--pgn-size-form-control-select-border-radius)","$custom-range-track-width":"var(--pgn-size-form-control-range-track-width)","$custom-range-track-height":"var(--pgn-size-form-control-range-track-height)","$custom-range-track-border-radius":"var(--pgn-size-form-control-range-track-border-radius)","$custom-range-thumb-width":"var(--pgn-size-form-control-range-thumb-width)","$custom-range-thumb-height":"var(--pgn-size-form-control-range-thumb-height)","$custom-range-thumb-border":"var(--pgn-size-form-control-range-thumb-border-base)","$custom-range-thumb-border-radius":"var(--pgn-size-form-control-range-thumb-border-radius)","$custom-range-thumb-focus-box-shadow-width":"var(--pgn-size-form-control-range-thumb-focus-width)","$custom-file-border-width":"var(--pgn-size-form-control-file-width)","$custom-file-height":"var(--pgn-size-form-control-file-height-base)","$custom-file-height-inner":"var(--pgn-size-form-control-file-height-inner)","$custom-file-border-radius":"var(--pgn-size-form-control-file-border-radius)","$form-control-icon-width":"var(--pgn-size-form-control-icon-width)","$custom-checkbox-indicator-border-radius":"var(--pgn-size-form-control-border-checkbox-indicator-radius)","$custom-radio-indicator-border-radius":"var(--pgn-size-form-control-border-radio-indicator-radius)","$form-grid-gutter-width":"var(--pgn-size-form-grid-gutter-width)","$form-autosuggest-icon-width":"var(--pgn-size-form-autosuggest-icon-width)","$form-autosuggest-icon-height":"var(--pgn-size-form-autosuggest-icon-height)","$form-autosuggest-spinner-width":"var(--pgn-size-form-autosuggest-spinner-width)","$form-autosuggest-spinner-height":"var(--pgn-size-form-autosuggest-spinner-height)","$form-autosuggest-border-width":"var(--pgn-size-form-autosuggest-border-width)","$form-check-focus-border-radius":"var(--pgn-size-form-border-radius-check-focus)","$form-check-border-width":"var(--pgn-size-form-border-radius-width)","$form-feedback-tooltip-border-radius":"var(--pgn-size-form-feedback-tooltip-border-radius)","$input-padding-y":"var(--pgn-spacing-form-input-padding-y-base)","$input-padding-y-sm":"var(--pgn-spacing-form-input-padding-y-sm)","$input-padding-y-lg":"var(--pgn-spacing-form-input-padding-y-lg)","$input-padding-x":"var(--pgn-spacing-form-input-padding-x-base)","$input-padding-x-sm":"var(--pgn-spacing-form-input-padding-x-sm)","$input-padding-x-lg":"var(--pgn-spacing-form-input-padding-x-lg)","$form-check-input-gutter":"var(--pgn-spacing-form-input-check-gutter)","$form-check-input-margin-x":"var(--pgn-spacing-form-input-check-margin-x-base)","$form-check-inline-input-margin-x":"var(--pgn-spacing-form-input-check-margin-x-inline)","$form-check-input-margin-y":"var(--pgn-spacing-form-input-check-margin-y)","$form-text-margin-top":"var(--pgn-spacing-form-text-margin-top)","$form-check-inline-margin-x":"var(--pgn-spacing-form-check-inline-margin-x)","$form-check-position-axis":"var(--pgn-spacing-form-check-position-axis)","$form-group-margin-bottom":"var(--pgn-spacing-form-group-margin-bottom)","$custom-control-gutter":"var(--pgn-spacing-form-control-gutter)","$custom-control-spacer-x":"var(--pgn-spacing-form-control-spacer-x)","$custom-select-padding-y":"var(--pgn-spacing-form-control-select-padding-y-base)","$custom-select-padding-y-sm":"var(--pgn-spacing-form-control-select-padding-y-sm)","$custom-select-padding-y-lg":"var(--pgn-spacing-form-control-select-padding-y-lg)","$custom-select-padding-x":"var(--pgn-spacing-form-control-select-padding-x-base)","$custom-select-padding-x-sm":"var(--pgn-spacing-form-control-select-padding-x-sm)","$custom-select-padding-x-lg":"var(--pgn-spacing-form-control-select-padding-x-lg)","$custom-select-indicator-padding":"var(--pgn-spacing-form-control-select-indicator-padding)","$custom-select-feedback-icon-padding-right":"var(--pgn-spacing-form-control-select-feedback-icon-padding-right)","$custom-select-feedback-icon-position":"var(--pgn-spacing-form-control-select-feedback-icon-position)","$form-feedback-margin-top":"var(--pgn-spacing-form-control-select-feedback-margin-top)","$form-feedback-tooltip-padding-y":"var(--pgn-spacing-form-control-select-feedback-tooltip-padding-y)","$form-feedback-tooltip-padding-x":"var(--pgn-spacing-form-control-select-feedback-tooltip-padding-x)","$select-icon-padding":"var(--pgn-spacing-form-control-select-icon-padding)","$custom-file-padding-y":"var(--pgn-spacing-form-control-file-padding-y)","$custom-file-padding-x":"var(--pgn-spacing-form-control-file-padding-x)","$input-transition":"var(--pgn-transition-form-input)","$custom-forms-transition":"var(--pgn-transition-form-control)","$input-font-family":"var(--pgn-typography-form-input-font-family)","$input-font-size":"var(--pgn-typography-form-input-font-size-base)","$input-font-size-sm":"var(--pgn-typography-form-input-font-size-sm)","$input-font-size-lg":"var(--pgn-typography-form-input-font-size-lg)","$input-font-weight":"var(--pgn-typography-form-input-font-weight)","$input-line-height":"var(--pgn-typography-form-input-line-height-base)","$input-line-height-sm":"var(--pgn-typography-form-input-line-height-sm)","$input-line-height-lg":"var(--pgn-typography-form-input-line-height-lg)","$custom-select-font-family":"var(--pgn-typography-form-control-select-font-family)","$custom-select-font-size":"var(--pgn-typography-form-control-select-font-size-base)","$custom-select-font-size-sm":"var(--pgn-typography-form-control-select-font-size-sm)","$custom-select-font-size-lg":"var(--pgn-typography-form-control-select-font-size-lg)","$custom-select-font-weight":"var(--pgn-typography-form-control-select-font-weight)","$custom-select-line-height":"var(--pgn-typography-form-control-select-line-height)","$custom-file-line-height":"var(--pgn-typography-form-control-file-line-height)","$custom-file-font-family":"var(--pgn-typography-form-control-file-font-family)","$custom-file-font-weight":"var(--pgn-typography-form-control-file-font-weight)","$form-feedback-font-size":"var(--pgn-typography-form-feedback-font-size)","$form-feedback-tooltip-font-size":"var(--pgn-typography-form-feedback-tooltip-font-size)","$form-feedback-tooltip-line-height":"var(--pgn-typography-form-feedback-tooltip-line-height)","$icon-inline":"var(--pgn-size-icon-inline)","$icon-sm":"var(--pgn-size-icon-sm)","$icon-md":"var(--pgn-size-icon-md)","$icon-lg":"var(--pgn-size-icon-lg)","$btn-icon-bg":"var(--pgn-color-icon-button-bg)","$btn-icon-accent-color":"var(--pgn-color-icon-button-accent)","$btn-icon-primary":"var(--pgn-color-icon-button-primary)","$btn-icon-secondary":"var(--pgn-color-icon-button-secondary)","$btn-icon-brand":"var(--pgn-color-icon-button-brand)","$btn-icon-success":"var(--pgn-color-icon-button-success)","$btn-icon-warning":"var(--pgn-color-icon-button-warning)","$btn-icon-danger":"var(--pgn-color-icon-button-danger)","$btn-icon-light":"var(--pgn-color-icon-button-light)","$btn-icon-dark":"var(--pgn-color-icon-button-dark)","$btn-icon-black":"var(--pgn-color-icon-button-black)","$btn-icon-diameter-md":"var(--pgn-size-icon-button-diameter-md)","$btn-icon-diameter-sm":"var(--pgn-size-icon-button-diameter-sm)","$btn-icon-diameter-inline":"var(--pgn-size-icon-button-diameter-inline)","$figure-caption-color":"var(--pgn-color-image-figure-caption)","$thumbnail-bg":"var(--pgn-color-image-thumbnail-bg)","$thumbnail-border-color":"var(--pgn-color-image-thumbnail-border)","$figure-caption-font-size":"var(--pgn-typography-image-figure-caption-font-size)","$thumbnail-box-shadow":"var(--pgn-elevation-image-thumbnail-box-shadow)","$thumbnail-border-width":"var(--pgn-size-image-thumbnail-border-width)","$thumbnail-border-radius":"var(--pgn-size-image-thumbnail-border-radius)","$thumbnail-padding":"var(--pgn-spacing-image-thumbnail-padding)","$active-background":"var(--pgn-color-menu-bg-active)","$border":"var(--pgn-color-menu-border-base)","$active-border":"var(--pgn-color-menu-border-active)","$hover-border":"var(--pgn-color-menu-border-hover)","$modal-content-bg":"var(--pgn-color-modal-content-bg)","$modal-content-border-color":"var(--pgn-color-modal-content-border)","$modal-backdrop-bg":"var(--pgn-color-modal-backdrop-bg)","$modal-content-box-shadow-sm-up":"var(--pgn-elevation-modal-content-box-shadow-sm-up)","$zindex-modal-backdrop":"var(--pgn-elevation-modal-backdrop-zindex)","$modal-backdrop-opacity":"var(--pgn-elevation-modal-backdrop-opacity)","$zindex-modal":"var(--pgn-elevation-modal-zindex)","$modal-xl":"var(--pgn-size-modal-xl)","$modal-lg":"var(--pgn-size-modal-lg)","$modal-md":"var(--pgn-size-modal-md)","$modal-sm":"var(--pgn-size-modal-sm)","$modal-content-border-width":"var(--pgn-size-modal-content-border-width)","$modal-content-border-radius":"var(--pgn-size-modal-content-border-radius)","$modal-inner-padding":"var(--pgn-spacing-modal-inner-padding-base)","$modal-inner-padding-bottom":"var(--pgn-spacing-modal-inner-padding-bottom)","$modal-footer-padding":"var(--pgn-spacing-modal-footer-padding-base)","$modal-footer-padding-y":"var(--pgn-spacing-modal-footer-padding-y)","$modal-header-padding":"var(--pgn-spacing-modal-header-padding-base)","$modal-header-padding-y":"var(--pgn-spacing-modal-header-padding-y)","$modal-dialog-margin":"var(--pgn-spacing-modal-dialog-margin)","$nav-tabs-link-active-border-color":"var(--pgn-border-color-nav-tabs-link-border-active)","$nav-tabs-link-hover-border-color":"var(--pgn-border-color-nav-tabs-link-border-hover)","$nav-link-color":"var(--pgn-color-nav-link-text-base)","$nav-link-disabled-color":"var(--pgn-color-nav-link-text-disabled)","$nav-tabs-border-color":"var(--pgn-color-nav-tabs-border)","$nav-tabs-link-hover-bg":"var(--pgn-color-nav-tabs-link-hover-bg)","$nav-tabs-link-active-color":"var(--pgn-color-nav-tabs-link-active-text)","$nav-tabs-link-active-bg":"var(--pgn-color-nav-tabs-link-active-bg)","$nav-pills-link-active-color":"var(--pgn-color-nav-pills-link-active-text)","$nav-pills-link-active-bg":"var(--pgn-color-nav-pills-link-active-bg)","$nav-divider-color":"var(--pgn-color-nav-divider)","$navbar-dark-color":"var(--pgn-color-navbar-dark-text)","$navbar-light-color":"var(--pgn-color-navbar-light-text)","$nav-link-font-weight":"var(--pgn-typography-nav-link-font-weight)","$nav-pills-border-radius":"var(--pgn-size-nav-pills-border-radius)","$nav-tabs-border-width":"var(--pgn-size-nav-tabs-border-width)","$nav-tabs-border-radius":"var(--pgn-size-nav-tabs-border-radius)","$nav-link-padding-y":"var(--pgn-spacing-nav-link-padding-y)","$nav-link-padding-x":"var(--pgn-spacing-nav-link-padding-x)","$nav-divider-margin-y":"var(--pgn-spacing-nav-divider-margin-y)","$navbar-dark-hover-color":"var(--pgn-color-navbar-dark-hover)","$navbar-dark-active-color":"var(--pgn-color-navbar-dark-active)","$navbar-dark-disabled-color":"var(--pgn-color-navbar-dark-disabled)","$navbar-dark-toggler-border-color":"var(--pgn-color-navbar-dark-toggler-border)","$navbar-dark-brand-color":"var(--pgn-color-navbar-dark-brand-text)","$navbar-dark-brand-hover-color":"var(--pgn-color-navbar-dark-brand-hover)","$navbar-light-hover-color":"var(--pgn-color-navbar-light-hover)","$navbar-light-active-color":"var(--pgn-color-navbar-light-active)","$navbar-light-disabled-color":"var(--pgn-color-navbar-light-disabled)","$navbar-light-toggler-border-color":"var(--pgn-color-navbar-light-toggler-border)","$navbar-light-brand-color":"var(--pgn-color-navbar-light-brand-text)","$navbar-light-brand-hover-color":"var(--pgn-color-navbar-light-brand-hover)","$navbar-padding-y":"var(--pgn-spacing-navbar-padding-y)","$navbar-padding-x":"var(--pgn-spacing-navbar-padding-x-base)","$navbar-nav-link-padding-x":"var(--pgn-spacing-navbar-padding-x-nav-link)","$navbar-brand-padding-y":"var(--pgn-spacing-navbar-brand-padding-y)","$navbar-toggler-padding-y":"var(--pgn-spacing-navbar-toggler-padding-y)","$navbar-toggler-padding-x":"var(--pgn-spacing-navbar-toggler-padding-x)","$navbar-brand-font-size":"var(--pgn-typography-navbar-brand-font-size)","$nav-link-height":"var(--pgn-typography-navbar-nav-link-height)","$navbar-toggler-font-size":"var(--pgn-typography-navbar-toggler-font-size)","$navbar-nav-scroll-max-height":"var(--pgn-size-navbar-nav-scroll-max-height)","$navbar-brand-height":"var(--pgn-size-navbar-brand-height)","$navbar-toggler-border-radius":"var(--pgn-size-navbar-toggler-border-radius)","$navbar-dark-toggler-icon-bg":"var(--pgn-content-navbar-toggler-dark-icon-bg)","$navbar-light-toggler-icon-bg":"var(--pgn-content-navbar-toggler-light-icon-bg)","$pagination-color":"var(--pgn-color-pagination-text-base)","$pagination-color-inverse":"var(--pgn-color-pagination-text-inverse)","$pagination-hover-color":"var(--pgn-color-pagination-text-hover)","$pagination-active-color":"var(--pgn-color-pagination-text-active)","$pagination-disabled-color":"var(--pgn-color-pagination-text-disabled)","$pagination-bg":"var(--pgn-color-pagination-bg-base)","$pagination-hover-bg":"var(--pgn-color-pagination-bg-hover)","$pagination-active-bg":"var(--pgn-color-pagination-bg-active)","$pagination-disabled-bg":"var(--pgn-color-pagination-bg-disabled)","$pagination-border-color":"var(--pgn-color-pagination-border-base)","$pagination-hover-border-color":"var(--pgn-color-pagination-border-hover)","$pagination-active-border-color":"var(--pgn-color-pagination-border-active)","$pagination-disabled-border-color":"var(--pgn-color-pagination-border-disabled)","$pagination-focus-color":"var(--pgn-color-pagination-focus-base)","$pagination-focus-color-text":"var(--pgn-color-pagination-focus-text)","$pagination-font-size-sm":"var(--pgn-typography-pagination-font-size-sm)","$pagination-line-height":"var(--pgn-typography-pagination-line-height)","$pagination-padding-y":"var(--pgn-spacing-pagination-padding-y-base)","$pagination-padding-y-sm":"var(--pgn-spacing-pagination-padding-y-sm)","$pagination-padding-y-lg":"var(--pgn-spacing-pagination-padding-y-lg)","$pagination-padding-x":"var(--pgn-spacing-pagination-padding-x-base)","$pagination-padding-x-sm":"var(--pgn-spacing-pagination-padding-x-sm)","$pagination-padding-x-lg":"var(--pgn-spacing-pagination-padding-x-lg)","$pagination-padding-icon":"var(--pgn-spacing-pagination-padding-icon)","$pagination-margin-x":"var(--pgn-spacing-pagination-margin-x)","$pagination-margin-y":"var(--pgn-spacing-pagination-margin-y)","$pagination-icon-size":"var(--pgn-size-pagination-icon-base)","$pagination-icon-size-sm":"var(--pgn-size-pagination-icon-sm)","$pagination-icon-width":"var(--pgn-size-pagination-icon-width)","$pagination-icon-height":"var(--pgn-size-pagination-icon-height)","$pagination-secondary-height":"var(--pgn-size-pagination-secondary-height-base)","$pagination-secondary-height-sm":"var(--pgn-size-pagination-secondary-height-sm)","$pagination-border-width":"var(--pgn-size-pagination-border-width)","$pagination-border-radius-sm":"var(--pgn-size-pagination-border-radius-sm)","$pagination-border-radius-lg":"var(--pgn-size-pagination-border-radius-lg)","$pagination-reduced-dropdown-max-height":"var(--pgn-size-pagination-reduced-dropdown-max-height)","$pagination-reduced-dropdown-min-width":"var(--pgn-size-pagination-reduced-dropdown-min-width)","$pagination-toggle-border":"var(--pgn-size-pagination-toggle-border-base)","$pagination-toggle-border-sm":"var(--pgn-size-pagination-toggle-border-sm)","$pagination-focus-border-width":"var(--pgn-size-pagination-focus-border-width)","$pagination-focus-outline":"var(--pgn-size-pagination-focus-outline)","$pagination-focus-box-shadow":"var(--pgn-elevation-pagination-focus-box-shadow)","$popover-font-size":"var(--pgn-typography-popover-font-size)","$popover-bg":"var(--pgn-color-popover-bg)","$popover-border-color":"var(--pgn-color-popover-border)","$popover-header-color":"var(--pgn-color-popover-header-text)","$popover-header-bg":"var(--pgn-color-popover-header-bg)","$popover-header-bg-dark":"var(--pgn-color-popover-header-bg-dark)","$popover-header-border-bottom-darken":"var(--pgn-color-popover-header-border-bottom-dark)","$popover-body-color":"var(--pgn-color-popover-body)","$popover-arrow-color":"var(--pgn-color-popover-arrow-base)","$popover-arrow-outer-color":"var(--pgn-color-popover-arrow-outer)","$popover-success-bg":"var(--pgn-color-popover-success-bg)","$popover-success-icon-color":"var(--pgn-color-popover-success-icon)","$popover-warning-bg":"var(--pgn-color-popover-warning-bg)","$popover-warning-icon-color":"var(--pgn-color-popover-warning-icon)","$popover-danger-bg":"var(--pgn-color-popover-danger-bg)","$popover-danger-icon-color":"var(--pgn-color-popover-danger-icon)","$popover-max-width":"var(--pgn-size-popover-max-width)","$popover-border-width":"var(--pgn-size-popover-border-width)","$popover-border-radius":"var(--pgn-size-popover-border-radius)","$popover-icon-height":"var(--pgn-size-popover-icon-height)","$popover-icon-width":"var(--pgn-size-popover-icon-width)","$popover-arrow-width":"var(--pgn-size-popover-arrow-width)","$popover-arrow-height":"var(--pgn-size-popover-arrow-height)","$popover-box-shadow":"var(--pgn-elevation-popover-box-shadow)","$zindex-popover":"var(--pgn-elevation-popover-zindex)","$popover-header-padding-y":"var(--pgn-spacing-popover-header-padding-y)","$popover-header-padding-x":"var(--pgn-spacing-popover-header-padding-x)","$popover-body-padding-y":"var(--pgn-spacing-popover-body-padding-y)","$popover-body-padding-x":"var(--pgn-spacing-popover-body-padding-x)","$popover-icon-margin-right":"var(--pgn-spacing-popover-icon-margin-right)","$checkpoint-background-color":"var(--pgn-color-product-tour-checkpoint-bg)","$checkpoint-body-color":"var(--pgn-color-product-tour-checkpoint-body)","$checkpoint-border-color":"var(--pgn-color-product-tour-checkpoint-border)","$checkpoint-breadcrumb-color":"var(--pgn-color-product-tour-checkpoint-breadcrumb)","$checkpoint-box-shadow-color":"var(--pgn-color-product-tour-checkpoint-box-shadow)","$checkpoint-arrow-border-top-color":"var(--pgn-color-product-tour-checkpoint-arrow-border-top)","$checkpoint-arrow-border-color-transparent":"var(--pgn-color-product-tour-checkpoint-arrow-border-transparent)","$checkpoint-border-width":"var(--pgn-size-product-tour-checkpoint-width-border)","$checkpoint-arrow-width":"var(--pgn-size-product-tour-checkpoint-width-arrow)","$checkpoint-max-width":"var(--pgn-size-product-tour-checkpoint-width-max)","$checkpoint-arrow-border-bottom":"var(--pgn-size-product-tour-checkpoint-arrow-bottom)","$checkpoint-arrow-border-top":"var(--pgn-size-product-tour-checkpoint-arrow-top)","$checkpoint-arrow-border-transparent":"var(--pgn-size-product-tour-checkpoint-arrow-transparent)","$checkpoint-z-index":"var(--pgn-elevation-product-tour-checkpoint-zindex)","$progress-bg":"var(--pgn-color-progress-bar-bg)","$progress-bar-border-color":"var(--pgn-color-progress-bar-border)","$progress-bar-color":"var(--pgn-color-progress-bar-bar-base)","$progress-bar-bg":"var(--pgn-color-progress-bar-bar-bg-base)","$annotated-progress-bar-bg":"var(--pgn-color-progress-bar-bar-bg-annotated)","$progress-font-size":"var(--pgn-typography-progress-bar-font-size)","$progress-height":"var(--pgn-size-progress-bar-height-base)","$annotated-progress-height":"var(--pgn-size-progress-bar-height-annotated)","$progress-bar-border-width":"var(--pgn-size-progress-bar-border-width)","$progress-border-radius":"var(--pgn-size-progress-bar-border-radius)","$progress-threshold-circle":"var(--pgn-size-progress-bar-threshold-circle)","$progress-box-shadow":"var(--pgn-elevation-progress-bar-box-shadow)","$progress-hint-annotation-gap":"var(--pgn-spacing-progress-bar-hint-annotation-gap)","$progress-bar-animation-timing":"var(--pgn-transition-progress-bar-bar-animation-timing)","$progress-bar-transition":"var(--pgn-transition-progress-bar-bar-transition)","$scrollable-body-box-shadow":"var(--pgn-elevation-scrollable-body-box-shadow)","$search-border-color":"var(--pgn-color-search-field-border-base)","$search-border-color-interaction":"var(--pgn-color-search-field-border-interaction)","$search-border-focus-color":"var(--pgn-color-search-field-border-focus)","$search-btn-primary-bg":"var(--pgn-color-search-field-button-bg-primary)","$search-btn-brand-bg":"var(--pgn-color-search-field-button-bg-brand)","$search-disabled-opacity":"var(--pgn-color-search-field-disabled-opacity)","$search-line-height":"var(--pgn-typography-search-field-line-height)","$search-border-width":"var(--pgn-size-search-field-border-width-base)","$search-border-width-interaction":"var(--pgn-size-search-field-border-width-interaction)","$search-border-focus-width":"var(--pgn-size-search-field-border-width-focus)","$search-border-radius":"var(--pgn-size-search-field-border-radius)","$input-height-search":"var(--pgn-size-search-field-search-input-height)","$search-button-margin":"var(--pgn-spacing-search-field-margin-button)","$selectable-box-padding":"var(--pgn-spacing-selectable-box-padding)","$selectable-box-border-radius":"var(--pgn-spacing-selectable-box-border-radius)","$selectable-box-space":"var(--pgn-spacing-selectable-box-box-space)","$sheet-skrim-bg":"var(--pgn-color-sheet-skrim-bg)","$sheet-skrim-component-box-shadow":"var(--pgn-color-sheet-skrim-component-box-shadow)","$zindex-sheet-backdrop":"var(--pgn-elevation-sheet-zindex-backdrop)","$zindex-sheet":"var(--pgn-elevation-sheet-zindex-main)","$spinner-width":"var(--pgn-size-spinner-base-width)","$spinner-height":"var(--pgn-size-spinner-base-height)","$spinner-border-width":"var(--pgn-size-spinner-base-border-width)","$spinner-width-sm":"var(--pgn-size-spinner-sm-width)","$spinner-height-sm":"var(--pgn-size-spinner-sm-height)","$spinner-border-width-sm":"var(--pgn-size-spinner-sm-border-width)","$stack-gap":"var(--pgn-size-stack-gap)","$sticky-shadow-top":"var(--pgn-elevation-sticky-shadow-top)","$sticky-shadow-bottom":"var(--pgn-elevation-sticky-shadow-bottom)","$sticky-offset":"var(--pgn-spacing-sticky-offset)","$tab-notification-height":"var(--pgn-size-tabs-notification-height)","$tab-notification-width":"var(--pgn-size-tabs-notification-width)","$tab-notification-font-size":"var(--pgn-typography-tabs-notification-font-size)","$toast-color":"var(--pgn-color-toast-base)","$toast-background-color":"var(--pgn-color-toast-bg)","$toast-border-color":"var(--pgn-color-toast-border)","$toast-header-color":"var(--pgn-color-toast-header-text)","$toast-header-background-color":"var(--pgn-color-toast-header-bg)","$toast-header-border-color":"var(--pgn-color-toast-header-border)","$toast-font-size":"var(--pgn-typography-toast-font-size)","$toast-box-shadow":"var(--pgn-elevation-toast-box-shadow)","$toast-max-width":"var(--pgn-size-toast-max-width)","$toast-border-width":"var(--pgn-size-toast-border-width)","$toast-border-radius":"var(--pgn-size-toast-border-radius)","$toast-padding-x":"var(--pgn-spacing-toast-padding-x)","$toast-padding-y":"var(--pgn-spacing-toast-padding-y)","$toast-container-gutter-lg":"var(--pgn-spacing-toast-container-gutter-lg)","$toast-container-gutter-sm":"var(--pgn-spacing-toast-container-gutter-sm)","$tooltip-font-size":"var(--pgn-typography-tooltip-font-size)","$tooltip-color":"var(--pgn-color-tooltip-text)","$tooltip-color-light":"var(--pgn-color-tooltip-light)","$tooltip-bg":"var(--pgn-color-tooltip-bg-base)","$tooltip-bg-light":"var(--pgn-color-tooltip-bg-light)","$tooltip-opacity":"var(--pgn-color-tooltip-opacity)","$tooltip-arrow-color":"var(--pgn-color-tooltip-arrow-base)","$tooltip-arrow-color-light":"var(--pgn-color-tooltip-arrow-light)","$tooltip-padding-y":"var(--pgn-spacing-tooltip-padding-y)","$tooltip-padding-x":"var(--pgn-spacing-tooltip-padding-x)","$tooltip-margin":"var(--pgn-spacing-tooltip-margin)","$tooltip-box-shadow":"var(--pgn-elevation-tooltip-box-shadow)","$zindex-tooltip":"var(--pgn-elevation-tooltip-zindex)","$tooltip-max-width":"var(--pgn-size-tooltip-max-width)","$tooltip-arrow-height":"var(--pgn-size-tooltip-arrow-height)","$tooltip-arrow-width":"var(--pgn-size-tooltip-arrow-width)","$tooltip-border-radius":"var(--pgn-size-tooltip-border-radius)","$body-bg":"var(--pgn-body-bg)","$body-color":"var(--pgn-body-color)","$caret-width":"var(--pgn-caret-width)","$caret-vertical-align":"var(--pgn-caret-vertical-align)","$caret-spacing":"var(--pgn-caret-spacing)","$headings-margin-bottom":"var(--pgn-headings-margin-bottom)","$headings-font-family":"var(--pgn-headings-font-family)","$headings-font-weight":"var(--pgn-headings-font-weight)","$headings-line-height":"var(--pgn-headings-line-height)","$headings-color":"var(--pgn-headings-color)","$hr-border-color":"var(--pgn-hr-border-color)","$hr-border-width":"var(--pgn-hr-border-width)","$hr-margin-y":"var(--pgn-hr-border-margin-y)","$input-btn-padding-y":"var(--pgn-input-btn-padding-y)","$input-btn-padding-x":"var(--pgn-input-btn-padding-x)","$input-btn-padding-y-sm":"var(--pgn-input-btn-padding-sm-y)","$input-btn-padding-x-sm":"var(--pgn-input-btn-padding-sm-x)","$input-btn-padding-y-lg":"var(--pgn-input-btn-padding-lg-y)","$input-btn-padding-x-lg":"var(--pgn-input-btn-padding-lg-x)","$input-btn-font-family":"var(--pgn-input-btn-font-family)","$input-btn-font-size":"var(--pgn-input-btn-font-size-base)","$input-btn-font-size-sm":"var(--pgn-input-btn-font-size-sm)","$input-btn-font-size-lg":"var(--pgn-input-btn-font-size-lg)","$input-btn-line-height":"var(--pgn-input-btn-line-height-base)","$input-btn-line-height-sm":"var(--pgn-input-btn-line-height-sm)","$input-btn-line-height-lg":"var(--pgn-input-btn-line-height-lg)","$input-btn-focus-width":"var(--pgn-input-btn-focus-width)","$input-btn-focus-color":"var(--pgn-input-btn-focus-color)","$input-btn-focus-box-shadow":"var(--pgn-input-btn-focus-box-shadow)","$input-btn-border-width":"var(--pgn-input-btn-border-width)","$link-color":"var(--pgn-link-color)","$link-decoration":"var(--pgn-link-decoration)","$link-hover-color":"var(--pgn-link-hover-color)","$link-hover-decoration":"var(--pgn-link-hover-decoration)","$inline-link-color":"var(--pgn-link-inline-color)","$inline-link-decoration":"var(--pgn-link-inline-decoration)","$inline-link-decoration-color":"var(--pgn-link-inline-decoration-color)","$inline-link-hover-color":"var(--pgn-link-inline-hover-color)","$inline-link-hover-decoration":"var(--pgn-link-inline-hover-decoration)","$inline-link-hover-decoration-color":"var(--pgn-link-inline-hover-decoration-color)","$muted-link-color":"var(--pgn-link-muted-color)","$muted-link-decoration":"var(--pgn-link-muted-decoration)","$muted-link-hover-color":"var(--pgn-link-muted-hover-color)","$muted-link-hover-decoration":"var(--pgn-link-muted-hover-decoration)","$muted-inline-link-color":"var(--pgn-link-muted-inline-color)","$muted-inline-link-decoration":"var(--pgn-link-muted-inline-decoration)","$muted-inline-link-decoration-color":"var(--pgn-link-muted-inline-decoration-color)","$muted-inline-link-hover-color":"var(--pgn-link-muted-inline-hover-color)","$muted-inline-link-hover-decoration":"var(--pgn-link-muted-inline-hover-decoration)","$muted-inline-link-hover-decoration-color":"var(--pgn-link-muted-inline-hover-decoration-color)","$brand-link-color":"var(--pgn-link-brand-color)","$brand-link-decoration":"var(--pgn-link-brand-decoration)","$brand-link-hover-color":"var(--pgn-link-brand-hover-color)","$brand-link-hover-decoration":"var(--pgn-link-brand-hover-decoration)","$brand-inline-link-color":"var(--pgn-link-brand-inline-color)","$brand-inline-link-decoration":"var(--pgn-link-brand-inline-decoration)","$brand-inline-link-decoration-color":"var(--pgn-link-brand-inline-decoration-color)","$brand-inline-link-hover-color":"var(--pgn-link-brand-inline-hover-color)","$brand-inline-link-hover-decoration":"var(--pgn-link-brand-inline-hover-decoration)","$brand-inline-link-hover-decoration-color":"var(--pgn-link-brand-inline-hover-decoration-color)","$emphasized-link-hover-darken-percentage":"var(--pgn-link-emphasized-hover-darken-percentage)","$dt-font-weight":"var(--pgn-dt-font-weight)","$list-inline-padding":"var(--pgn-list-inline-padding)","$list-group-color":"var(--pgn-list-group-color)","$list-group-bg":"var(--pgn-list-group-bg-base)","$list-group-hover-bg":"var(--pgn-list-group-bg-hover)","$list-group-border-color":"var(--pgn-list-group-border-color)","$list-group-border-width":"var(--pgn-list-group-border-width)","$list-group-border-radius":"var(--pgn-list-group-border-radius)","$list-group-item-padding-y":"var(--pgn-list-group-item-padding-y)","$list-group-item-padding-x":"var(--pgn-list-group-item-padding-x)","$list-group-active-color":"var(--pgn-list-group-active-color-base)","$list-group-active-border-color":"var(--pgn-list-group-active-color-border)","$list-group-active-bg":"var(--pgn-list-group-active-bg)","$list-group-disabled-color":"var(--pgn-list-group-disabled-color)","$list-group-disabled-bg":"var(--pgn-list-group-disabled-bg)","$list-group-action-color":"var(--pgn-list-group-action-color-base)","$list-group-action-hover-color":"var(--pgn-list-group-action-color-hover)","$list-group-action-active-color":"var(--pgn-list-group-action-active-color)","$list-group-action-active-bg":"var(--pgn-list-group-action-active-bg)","$text-muted":"var(--pgn-text-muted)","$paragraph-margin-bottom":"var(--pgn-paragraph-margin-bottom)","$blockquote-small-font-size":"var(--pgn-blockquote-small-font-size)","$blockquote-font-size":"var(--pgn-blockquote-font-size)","$mark-padding":"var(--pgn-mark-padding)","$mark-bg":"var(--pgn-mark-bg)","$white":"var(--pgn-color-white)","$black":"var(--pgn-color-black)","$blue":"var(--pgn-color-blue)","$red":"var(--pgn-color-red)","$green":"var(--pgn-color-green)","$yellow":"var(--pgn-color-yellow)","$teal":"var(--pgn-color-teal)","$accent-a":"var(--pgn-color-accent-a)","$accent-b":"var(--pgn-color-accent-b)","$gray-100":"var(--pgn-color-gray-100)","$gray-200":"var(--pgn-color-gray-200)","$gray-300":"var(--pgn-color-gray-300)","$gray-400":"var(--pgn-color-gray-400)","$gray-500":"var(--pgn-color-gray-500)","$gray-600":"var(--pgn-color-gray-600)","$gray-700":"var(--pgn-color-gray-700)","$gray-800":"var(--pgn-color-gray-800)","$gray-900":"var(--pgn-color-gray-900)","$gray":"var(--pgn-color-gray-base)","$primary-100":"var(--pgn-color-primary-100)","$primary-200":"var(--pgn-color-primary-200)","$primary-300":"var(--pgn-color-primary-300)","$primary-400":"var(--pgn-color-primary-400)","$primary-500":"var(--pgn-color-primary-500)","$primary-600":"var(--pgn-color-primary-600)","$primary-700":"var(--pgn-color-primary-700)","$primary-800":"var(--pgn-color-primary-800)","$primary-900":"var(--pgn-color-primary-900)","$primary":"var(--pgn-color-primary-base)","$secondary-100":"var(--pgn-color-secondary-100)","$secondary-200":"var(--pgn-color-secondary-200)","$secondary-300":"var(--pgn-color-secondary-300)","$secondary-400":"var(--pgn-color-secondary-400)","$secondary-500":"var(--pgn-color-secondary-500)","$secondary-600":"var(--pgn-color-secondary-600)","$secondary-700":"var(--pgn-color-secondary-700)","$secondary-800":"var(--pgn-color-secondary-800)","$secondary-900":"var(--pgn-color-secondary-900)","$secondary":"var(--pgn-color-secondary-base)","$brand-100":"var(--pgn-color-brand-100)","$brand-200":"var(--pgn-color-brand-200)","$brand-300":"var(--pgn-color-brand-300)","$brand-400":"var(--pgn-color-brand-400)","$brand-500":"var(--pgn-color-brand-500)","$brand-600":"var(--pgn-color-brand-600)","$brand-700":"var(--pgn-color-brand-700)","$brand-800":"var(--pgn-color-brand-800)","$brand-900":"var(--pgn-color-brand-900)","$brand":"var(--pgn-color-brand-base)","$success-100":"var(--pgn-color-success-100)","$success-200":"var(--pgn-color-success-200)","$success-300":"var(--pgn-color-success-300)","$success-400":"var(--pgn-color-success-400)","$success-500":"var(--pgn-color-success-500)","$success-600":"var(--pgn-color-success-600)","$success-700":"var(--pgn-color-success-700)","$success-800":"var(--pgn-color-success-800)","$success-900":"var(--pgn-color-success-900)","$success":"var(--pgn-color-success-base)","$info-100":"var(--pgn-color-info-100)","$info-200":"var(--pgn-color-info-200)","$info-300":"var(--pgn-color-info-300)","$info-400":"var(--pgn-color-info-400)","$info-500":"var(--pgn-color-info-500)","$info-600":"var(--pgn-color-info-600)","$info-700":"var(--pgn-color-info-700)","$info-800":"var(--pgn-color-info-800)","$info-900":"var(--pgn-color-info-900)","$info":"var(--pgn-color-info-base)","$warning-100":"var(--pgn-color-warning-100)","$warning-200":"var(--pgn-color-warning-200)","$warning-300":"var(--pgn-color-warning-300)","$warning-400":"var(--pgn-color-warning-400)","$warning-500":"var(--pgn-color-warning-500)","$warning-600":"var(--pgn-color-warning-600)","$warning-700":"var(--pgn-color-warning-700)","$warning-800":"var(--pgn-color-warning-800)","$warning-900":"var(--pgn-color-warning-900)","$warning":"var(--pgn-color-warning-base)","$danger-100":"var(--pgn-color-danger-100)","$danger-200":"var(--pgn-color-danger-200)","$danger-300":"var(--pgn-color-danger-300)","$danger-400":"var(--pgn-color-danger-400)","$danger-500":"var(--pgn-color-danger-500)","$danger-600":"var(--pgn-color-danger-600)","$danger-700":"var(--pgn-color-danger-700)","$danger-800":"var(--pgn-color-danger-800)","$danger-900":"var(--pgn-color-danger-900)","$danger":"var(--pgn-color-danger-base)","$light-100":"var(--pgn-color-light-100)","$light-200":"var(--pgn-color-light-200)","$light-300":"var(--pgn-color-light-300)","$light-400":"var(--pgn-color-light-400)","$light-500":"var(--pgn-color-light-500)","$light-600":"var(--pgn-color-light-600)","$light-700":"var(--pgn-color-light-700)","$light-800":"var(--pgn-color-light-800)","$light-900":"var(--pgn-color-light-900)","$light":"var(--pgn-color-light-base)","$dark-100":"var(--pgn-color-dark-100)","$dark-200":"var(--pgn-color-dark-200)","$dark-300":"var(--pgn-color-dark-300)","$dark-400":"var(--pgn-color-dark-400)","$dark-500":"var(--pgn-color-dark-500)","$dark-600":"var(--pgn-color-dark-600)","$dark-700":"var(--pgn-color-dark-700)","$dark-800":"var(--pgn-color-dark-800)","$dark-900":"var(--pgn-color-dark-900)","$dark":"var(--pgn-color-dark-base)","$display1-size":"var(--pgn-display-size-1)","$display2-size":"var(--pgn-display-size-2)","$display3-size":"var(--pgn-display-size-3)","$display4-size":"var(--pgn-display-size-4)","$display-mobile-size":"var(--pgn-display-size-mobile)","$display1-weight":"var(--pgn-display-weight-1)","$display2-weight":"var(--pgn-display-weight-2)","$display3-weight":"var(--pgn-display-weight-3)","$display4-weight":"var(--pgn-display-weight-4)","$display-line-height":"var(--pgn-display-line-height-base)","$display-mobile-line-height":"var(--pgn-display-line-height-mobile)","$level-1-box-shadow":"var(--pgn-box-shadow-level-1)","$level-2-box-shadow":"var(--pgn-box-shadow-level-2)","$level-3-box-shadow":"var(--pgn-box-shadow-level-3)","$level-4-box-shadow":"var(--pgn-box-shadow-level-4)","$level-5-box-shadow":"var(--pgn-box-shadow-level-5)","$box-shadow":"var(--pgn-box-shadow-base)","$box-shadow-sm":"var(--pgn-box-shadow-sm)","$box-shadow-lg":"var(--pgn-box-shadow-lg)","$box-shadow-down-1":"var(--pgn-box-shadow-down-1)","$box-shadow-down-2":"var(--pgn-box-shadow-down-2)","$box-shadow-down-3":"var(--pgn-box-shadow-down-3)","$box-shadow-down-4":"var(--pgn-box-shadow-down-4)","$box-shadow-down-5":"var(--pgn-box-shadow-down-5)","$box-shadow-left-1":"var(--pgn-box-shadow-left-1)","$box-shadow-left-2":"var(--pgn-box-shadow-left-2)","$box-shadow-left-3":"var(--pgn-box-shadow-left-3)","$box-shadow-left-4":"var(--pgn-box-shadow-left-4)","$box-shadow-left-5":"var(--pgn-box-shadow-left-5)","$box-shadow-up-1":"var(--pgn-box-shadow-up-1)","$box-shadow-up-2":"var(--pgn-box-shadow-up-2)","$box-shadow-up-3":"var(--pgn-box-shadow-up-3)","$box-shadow-up-4":"var(--pgn-box-shadow-up-4)","$box-shadow-up-5":"var(--pgn-box-shadow-up-5)","$box-shadow-right-1":"var(--pgn-box-shadow-right-1)","$box-shadow-right-2":"var(--pgn-box-shadow-right-2)","$box-shadow-right-3":"var(--pgn-box-shadow-right-3)","$box-shadow-right-4":"var(--pgn-box-shadow-right-4)","$box-shadow-right-5":"var(--pgn-box-shadow-right-5)","$box-shadow-centered-1":"var(--pgn-box-shadow-centered-1)","$box-shadow-centered-2":"var(--pgn-box-shadow-centered-2)","$box-shadow-centered-3":"var(--pgn-box-shadow-centered-3)","$box-shadow-centered-4":"var(--pgn-box-shadow-centered-4)","$box-shadow-centered-5":"var(--pgn-box-shadow-centered-5)","$zindex-sticky":"var(--pgn-zindex-sticky)","$zindex-fixed":"var(--pgn-zindex-fixed)","$theme-color-interval":"var(--pgn-theme-interval)","$spacer":"var(--pgn-spacer-base)","$transition-base":"var(--pgn-transition-base)","$transition-fade":"var(--pgn-transition-fade)","$transition-collapse":"var(--pgn-transition-collapse)","$font-family-base":"var(--pgn-font-family-base)","$font-family-sans-serif":"var(--pgn-font-family-sans-serif)","$font-family-serif":"var(--pgn-font-family-serif)","$font-family-monospace":"var(--pgn-font-family-monospace)","$font-size-base":"var(--pgn-font-size-base)","$font-size-lg":"var(--pgn-font-size-lg)","$font-size-sm":"var(--pgn-font-size-sm)","$font-size-xs":"var(--pgn-font-size-xs)","$small-font-size":"var(--pgn-font-size-small-base)","$x-small-font-size":"var(--pgn-font-size-small-x)","$h1-font-size":"var(--pgn-font-size-h1)","$h2-font-size":"var(--pgn-font-size-h2)","$h3-font-size":"var(--pgn-font-size-h3)","$h4-font-size":"var(--pgn-font-size-h4)","$h5-font-size":"var(--pgn-font-size-h5)","$h6-font-size":"var(--pgn-font-size-h6)","$h1-mobile-font-size":"var(--pgn-font-size-mobile-h1)","$h2-mobile-font-size":"var(--pgn-font-size-mobile-h2)","$h3-mobile-font-size":"var(--pgn-font-size-mobile-h3)","$h4-mobile-font-size":"var(--pgn-font-size-mobile-h4)","$h5-mobile-font-size":"var(--pgn-font-size-mobile-h5)","$h6-mobile-font-size":"var(--pgn-font-size-mobile-h6)","$lead-font-size":"var(--pgn-font-size-lead)","$font-weight-lighter":"var(--pgn-font-weight-lighter)","$font-weight-light":"var(--pgn-font-weight-light)","$font-weight-normal":"var(--pgn-font-weight-normal)","$font-weight-semi-bold":"var(--pgn-font-weight-semi-bold)","$font-weight-bold":"var(--pgn-font-weight-bold)","$font-weight-bolder":"var(--pgn-font-weight-bolder)","$font-weight-base":"var(--pgn-font-weight-base)","$lead-font-weight":"var(--pgn-font-weight-lead)","$line-height-base":"var(--pgn-line-height-base)","$line-height-lg":"var(--pgn-line-height-lg)","$line-height-sm":"var(--pgn-line-height-sm)"}